<?xml version="1.0" encoding="utf-8"?>
          <actions>
          <action>
            <action_id>create_Content_Container_Template_4213423429</action_id>
            <action_type>create_asset</action_type>
            <type_code>Content_Container_Template</type_code>
            <link_type>1</link_type>
            <parentid>1</parentid>
            <value></value>
            <is_dependant>0</is_dependant>
            <is_exclusive>0</is_exclusive>
          </action>
          <action>
            <action_id>set_Content_Container_Template_4213423429_name</action_id>
            <action_type>set_attribute_value</action_type>
            <asset>[[output://create_Content_Container_Template_4213423429.assetid]]</asset>
            <attribute>name</attribute>
            <value><![CDATA[Banner - Intermediate]]></value>
          </action>

          <action>
            <action_id>set_Content_Container_Template_4213423429_edit_interface_in_admin</action_id>
            <action_type>set_attribute_value</action_type>
            <asset>[[output://create_Content_Container_Template_4213423429.assetid]]</asset>
            <attribute>edit_interface_in_admin</attribute>
            <value><![CDATA[1]]></value>
          </action>

          <action>
            <action_id>set_Content_Container_Template_4213423429_icon_color</action_id>
            <action_type>set_attribute_value</action_type>
            <asset>[[output://create_Content_Container_Template_4213423429.assetid]]</asset>
            <attribute>icon_color</attribute>
            <value><![CDATA[blue]]></value>
          </action>
          
          <action>
          <action_id>create_Metadata_Schema_6365543312</action_id>
          <action_type>create_asset</action_type>
          <type_code>Metadata_Schema</type_code>
          <link_type>1</link_type>
          <parentid>[[output://create_Content_Container_Template_4213423429.assetid]]</parentid>
          <value></value>
          <is_dependant>0</is_dependant>
          <is_exclusive>0</is_exclusive>
          </action>
          <action>
            <action_id>set_Metadata_Schema_6365543312_name</action_id>
            <action_type>set_attribute_value</action_type>
            <asset>[[output://create_Metadata_Schema_6365543312.assetid]]</asset>
            <attribute>name</attribute>
            <value><![CDATA[Banner - Intermediate]]></value>
          </action>
          <action>
              <action_id>set_permission_6365543312_read_5</action_id>
              <action_type>set_permission</action_type>
              <asset>[[output://create_Metadata_Schema_6365543312.assetid]]</asset>
              <permission>1</permission>
              <granted>1</granted>
              <userid>[[system://public_user]]</userid>
          </action>
          
          <action>
            <action_id>create_Metadata_Section_912922464</action_id>
            <action_type>create_asset</action_type>
            <type_code>Metadata_Section</type_code>
            <link_type>2</link_type>
            <parentid>[[output://create_Metadata_Schema_6365543312.assetid]]</parentid>
            <value></value>
            <is_dependant>1</is_dependant>
            <is_exclusive>0</is_exclusive>
          </action>
          <action>
            <action_id>add_Metadata_Section_912922464_path</action_id>
            <action_type>add_web_path</action_type>
            <asset>[[output://create_Metadata_Section_912922464.assetid]]</asset>
            <parent_asset>[[output://create_Metadata_Schema_6365543312.assetid]]</parent_asset>
            <path>settings</path>
          </action>
          <action>
            <action_id>set_Metadata_Section_912922464_name</action_id>
            <action_type>set_attribute_value</action_type>
            <asset>[[output://create_Metadata_Section_912922464.assetid]]</asset>
            <attribute>name</attribute>
            <value><![CDATA[Settings]]></value>
          </action>
          <action>
              <action_id>set_permission_912922464_read_5</action_id>
              <action_type>set_permission</action_type>
              <asset>[[output://create_Metadata_Section_912922464.assetid]]</asset>
              <permission>1</permission>
              <granted>1</granted>
              <userid>[[system://public_user]]</userid>
          </action>           
          
              <action>
                  <action_id>create_metadata_field_select_3858758022</action_id>
                  <action_type>create_asset</action_type>
                  <type_code>metadata_field_select</type_code>
                  <link_type>2</link_type>
                  <parentid>[[output://create_Metadata_Section_912922464.assetid]]</parentid>
                  <value></value>
                  <is_dependant>1</is_dependant>
                  <is_exclusive>0</is_exclusive>
              </action> 
              <action>
                  <action_id>set_metadata_field_select_3858758022_name</action_id>
                  <action_type>set_attribute_value</action_type>
                  <asset>[[output://create_metadata_field_select_3858758022.assetid]]</asset>
                  <attribute>name</attribute>
                  <value><![CDATA[breadcrumbs_display]]></value>
              </action>
              <action>
                  <action_id>set_metadata_field_select_3858758022_friendly_name</action_id>
                  <action_type>set_attribute_value</action_type>
                  <asset>[[output://create_metadata_field_select_3858758022.assetid]]</asset>
                  <attribute>friendly_name</attribute>
                  <value><![CDATA[Display Breadcrumbs?]]></value>
              </action>
              <action>
                  <action_id>set_metadata_field_select_3858758022_default</action_id>
                  <action_type>set_attribute_value</action_type>
                  <asset>[[output://create_metadata_field_select_3858758022.assetid]]</asset>
                  <attribute>default</attribute>
                  <value><![CDATA[yes]]></value>
              </action>
              <action>
                  <action_id>set_metadata_field_select_3858758022_description</action_id>
                  <action_type>set_attribute_value</action_type>
                  <asset>[[output://create_metadata_field_select_3858758022.assetid]]</asset>
                  <attribute>description</attribute>
                  <value><![CDATA[]]></value>
              </action>
              <action>
                  <action_id>set_metadata_field_select_3858758022_editable</action_id>
                  <action_type>set_attribute_value</action_type>
                  <asset>[[output://create_metadata_field_select_3858758022.assetid]]</asset>
                  <attribute>editable</attribute>
                  <value><![CDATA[1]]></value>
              </action>
              <action>
                  <action_id>set_metadata_field_select_3858758022_editable</action_id>
                  <action_type>set_attribute_value</action_type>
                  <asset>[[output://create_metadata_field_select_3858758022.assetid]]</asset>
                  <attribute>editable</attribute>
                  <value><![CDATA[1]]></value>
              </action>
              <action>
                  <action_id>set_metadata_field_select_3858758022_required</action_id>
                  <action_type>set_attribute_value</action_type>
                  <asset>[[output://create_metadata_field_select_3858758022.assetid]]</asset>
                  <attribute>required</attribute>
                  <value><![CDATA[0]]></value>
              </action>
              <action>
                  <action_id>set_permission_3858758022_read_5</action_id>
                  <action_type>set_permission</action_type>
                  <asset>[[output://create_metadata_field_select_3858758022.assetid]]</asset>
                  <permission>1</permission>
                  <granted>1</granted>
                  <userid>[[system://public_user]]</userid>
              </action>
              
                  <action>
                      <action_id>set_metadata_field_select_3858758022_select_options</action_id>
                      <action_type>set_attribute_value</action_type>
                      <asset>[[output://create_metadata_field_select_3858758022.assetid]]</asset>
                      <attribute>select_options</attribute>
                      <value><![CDATA[array ('' => 'No','yes' => 'Yes',);]]></value>
                  </action>
                  <action>
                      <action_id>set_{f.type}_3858758022_edit_params</action_id>
                      <action_type>set_attribute_value</action_type>
                      <asset>[[output://create_metadata_field_select_3858758022.assetid]]</asset>
                      <attribute>edit_params</attribute>
                      <value><![CDATA[array (
                      'style' => 'list',
                      'type' => 'table',
                      'height' => '',
                      'columns' => '1',
                      'empty_text' => '',
                      'extras' => '',
                      );]]></value>
                  </action>  
                  
              <action>
                  <action_id>create_metadata_field_text_3868001804</action_id>
                  <action_type>create_asset</action_type>
                  <type_code>metadata_field_text</type_code>
                  <link_type>2</link_type>
                  <parentid>[[output://create_Metadata_Section_912922464.assetid]]</parentid>
                  <value></value>
                  <is_dependant>1</is_dependant>
                  <is_exclusive>0</is_exclusive>
              </action> 
              <action>
                  <action_id>set_metadata_field_text_3868001804_name</action_id>
                  <action_type>set_attribute_value</action_type>
                  <asset>[[output://create_metadata_field_text_3868001804.assetid]]</asset>
                  <attribute>name</attribute>
                  <value><![CDATA[heading_primary]]></value>
              </action>
              <action>
                  <action_id>set_metadata_field_text_3868001804_friendly_name</action_id>
                  <action_type>set_attribute_value</action_type>
                  <asset>[[output://create_metadata_field_text_3868001804.assetid]]</asset>
                  <attribute>friendly_name</attribute>
                  <value><![CDATA[Primary Heading]]></value>
              </action>
              <action>
                  <action_id>set_metadata_field_text_3868001804_default</action_id>
                  <action_type>set_attribute_value</action_type>
                  <asset>[[output://create_metadata_field_text_3868001804.assetid]]</asset>
                  <attribute>default</attribute>
                  <value><![CDATA[Banner Intermediate]]></value>
              </action>
              <action>
                  <action_id>set_metadata_field_text_3868001804_description</action_id>
                  <action_type>set_attribute_value</action_type>
                  <asset>[[output://create_metadata_field_text_3868001804.assetid]]</asset>
                  <attribute>description</attribute>
                  <value><![CDATA[]]></value>
              </action>
              <action>
                  <action_id>set_metadata_field_text_3868001804_editable</action_id>
                  <action_type>set_attribute_value</action_type>
                  <asset>[[output://create_metadata_field_text_3868001804.assetid]]</asset>
                  <attribute>editable</attribute>
                  <value><![CDATA[1]]></value>
              </action>
              <action>
                  <action_id>set_metadata_field_text_3868001804_editable</action_id>
                  <action_type>set_attribute_value</action_type>
                  <asset>[[output://create_metadata_field_text_3868001804.assetid]]</asset>
                  <attribute>editable</attribute>
                  <value><![CDATA[1]]></value>
              </action>
              <action>
                  <action_id>set_metadata_field_text_3868001804_required</action_id>
                  <action_type>set_attribute_value</action_type>
                  <asset>[[output://create_metadata_field_text_3868001804.assetid]]</asset>
                  <attribute>required</attribute>
                  <value><![CDATA[0]]></value>
              </action>
              <action>
                  <action_id>set_permission_3868001804_read_5</action_id>
                  <action_type>set_permission</action_type>
                  <asset>[[output://create_metadata_field_text_3868001804.assetid]]</asset>
                  <permission>1</permission>
                  <granted>1</granted>
                  <userid>[[system://public_user]]</userid>
              </action>
              
              <action>
                  <action_id>create_metadata_field_text_7132442851</action_id>
                  <action_type>create_asset</action_type>
                  <type_code>metadata_field_text</type_code>
                  <link_type>2</link_type>
                  <parentid>[[output://create_Metadata_Section_912922464.assetid]]</parentid>
                  <value></value>
                  <is_dependant>1</is_dependant>
                  <is_exclusive>0</is_exclusive>
              </action> 
              <action>
                  <action_id>set_metadata_field_text_7132442851_name</action_id>
                  <action_type>set_attribute_value</action_type>
                  <asset>[[output://create_metadata_field_text_7132442851.assetid]]</asset>
                  <attribute>name</attribute>
                  <value><![CDATA[heading_secondary]]></value>
              </action>
              <action>
                  <action_id>set_metadata_field_text_7132442851_friendly_name</action_id>
                  <action_type>set_attribute_value</action_type>
                  <asset>[[output://create_metadata_field_text_7132442851.assetid]]</asset>
                  <attribute>friendly_name</attribute>
                  <value><![CDATA[Secondary Heading]]></value>
              </action>
              <action>
                  <action_id>set_metadata_field_text_7132442851_default</action_id>
                  <action_type>set_attribute_value</action_type>
                  <asset>[[output://create_metadata_field_text_7132442851.assetid]]</asset>
                  <attribute>default</attribute>
                  <value><![CDATA[Heading Secondary]]></value>
              </action>
              <action>
                  <action_id>set_metadata_field_text_7132442851_description</action_id>
                  <action_type>set_attribute_value</action_type>
                  <asset>[[output://create_metadata_field_text_7132442851.assetid]]</asset>
                  <attribute>description</attribute>
                  <value><![CDATA[]]></value>
              </action>
              <action>
                  <action_id>set_metadata_field_text_7132442851_editable</action_id>
                  <action_type>set_attribute_value</action_type>
                  <asset>[[output://create_metadata_field_text_7132442851.assetid]]</asset>
                  <attribute>editable</attribute>
                  <value><![CDATA[1]]></value>
              </action>
              <action>
                  <action_id>set_metadata_field_text_7132442851_editable</action_id>
                  <action_type>set_attribute_value</action_type>
                  <asset>[[output://create_metadata_field_text_7132442851.assetid]]</asset>
                  <attribute>editable</attribute>
                  <value><![CDATA[1]]></value>
              </action>
              <action>
                  <action_id>set_metadata_field_text_7132442851_required</action_id>
                  <action_type>set_attribute_value</action_type>
                  <asset>[[output://create_metadata_field_text_7132442851.assetid]]</asset>
                  <attribute>required</attribute>
                  <value><![CDATA[0]]></value>
              </action>
              <action>
                  <action_id>set_permission_7132442851_read_5</action_id>
                  <action_type>set_permission</action_type>
                  <asset>[[output://create_metadata_field_text_7132442851.assetid]]</asset>
                  <permission>1</permission>
                  <granted>1</granted>
                  <userid>[[system://public_user]]</userid>
              </action>
              
              <action>
                  <action_id>create_metadata_field_select_2843994634</action_id>
                  <action_type>create_asset</action_type>
                  <type_code>metadata_field_select</type_code>
                  <link_type>2</link_type>
                  <parentid>[[output://create_Metadata_Section_912922464.assetid]]</parentid>
                  <value></value>
                  <is_dependant>1</is_dependant>
                  <is_exclusive>0</is_exclusive>
              </action> 
              <action>
                  <action_id>set_metadata_field_select_2843994634_name</action_id>
                  <action_type>set_attribute_value</action_type>
                  <asset>[[output://create_metadata_field_select_2843994634.assetid]]</asset>
                  <attribute>name</attribute>
                  <value><![CDATA[heading_background_display]]></value>
              </action>
              <action>
                  <action_id>set_metadata_field_select_2843994634_friendly_name</action_id>
                  <action_type>set_attribute_value</action_type>
                  <asset>[[output://create_metadata_field_select_2843994634.assetid]]</asset>
                  <attribute>friendly_name</attribute>
                  <value><![CDATA[Display block background?]]></value>
              </action>
              <action>
                  <action_id>set_metadata_field_select_2843994634_default</action_id>
                  <action_type>set_attribute_value</action_type>
                  <asset>[[output://create_metadata_field_select_2843994634.assetid]]</asset>
                  <attribute>default</attribute>
                  <value><![CDATA[no]]></value>
              </action>
              <action>
                  <action_id>set_metadata_field_select_2843994634_description</action_id>
                  <action_type>set_attribute_value</action_type>
                  <asset>[[output://create_metadata_field_select_2843994634.assetid]]</asset>
                  <attribute>description</attribute>
                  <value><![CDATA[]]></value>
              </action>
              <action>
                  <action_id>set_metadata_field_select_2843994634_editable</action_id>
                  <action_type>set_attribute_value</action_type>
                  <asset>[[output://create_metadata_field_select_2843994634.assetid]]</asset>
                  <attribute>editable</attribute>
                  <value><![CDATA[1]]></value>
              </action>
              <action>
                  <action_id>set_metadata_field_select_2843994634_editable</action_id>
                  <action_type>set_attribute_value</action_type>
                  <asset>[[output://create_metadata_field_select_2843994634.assetid]]</asset>
                  <attribute>editable</attribute>
                  <value><![CDATA[1]]></value>
              </action>
              <action>
                  <action_id>set_metadata_field_select_2843994634_required</action_id>
                  <action_type>set_attribute_value</action_type>
                  <asset>[[output://create_metadata_field_select_2843994634.assetid]]</asset>
                  <attribute>required</attribute>
                  <value><![CDATA[0]]></value>
              </action>
              <action>
                  <action_id>set_permission_2843994634_read_5</action_id>
                  <action_type>set_permission</action_type>
                  <asset>[[output://create_metadata_field_select_2843994634.assetid]]</asset>
                  <permission>1</permission>
                  <granted>1</granted>
                  <userid>[[system://public_user]]</userid>
              </action>
              
                  <action>
                      <action_id>set_metadata_field_select_2843994634_select_options</action_id>
                      <action_type>set_attribute_value</action_type>
                      <asset>[[output://create_metadata_field_select_2843994634.assetid]]</asset>
                      <attribute>select_options</attribute>
                      <value><![CDATA[array ('' => 'No','yes' => 'Yes',);]]></value>
                  </action>
                  <action>
                      <action_id>set_{f.type}_2843994634_edit_params</action_id>
                      <action_type>set_attribute_value</action_type>
                      <asset>[[output://create_metadata_field_select_2843994634.assetid]]</asset>
                      <attribute>edit_params</attribute>
                      <value><![CDATA[array (
                      'style' => 'list',
                      'type' => 'table',
                      'height' => '',
                      'columns' => '1',
                      'empty_text' => '',
                      'extras' => '',
                      );]]></value>
                  </action>  
                  
              <action>
                  <action_id>create_metadata_field_wysiwyg_1693525114</action_id>
                  <action_type>create_asset</action_type>
                  <type_code>metadata_field_wysiwyg</type_code>
                  <link_type>2</link_type>
                  <parentid>[[output://create_Metadata_Section_912922464.assetid]]</parentid>
                  <value></value>
                  <is_dependant>1</is_dependant>
                  <is_exclusive>0</is_exclusive>
              </action> 
              <action>
                  <action_id>set_metadata_field_wysiwyg_1693525114_name</action_id>
                  <action_type>set_attribute_value</action_type>
                  <asset>[[output://create_metadata_field_wysiwyg_1693525114.assetid]]</asset>
                  <attribute>name</attribute>
                  <value><![CDATA[abstract]]></value>
              </action>
              <action>
                  <action_id>set_metadata_field_wysiwyg_1693525114_friendly_name</action_id>
                  <action_type>set_attribute_value</action_type>
                  <asset>[[output://create_metadata_field_wysiwyg_1693525114.assetid]]</asset>
                  <attribute>friendly_name</attribute>
                  <value><![CDATA[Abstract]]></value>
              </action>
              <action>
                  <action_id>set_metadata_field_wysiwyg_1693525114_default</action_id>
                  <action_type>set_attribute_value</action_type>
                  <asset>[[output://create_metadata_field_wysiwyg_1693525114.assetid]]</asset>
                  <attribute>default</attribute>
                  <value><![CDATA[<p>Lorem ipsum dolor sit amet, consectetur adipiscing elit, sed do eiusmod tempor incididunt ut labore et dolore magna aliqua. Ut enim ad minim veniam, quis nostrud exercitation ullamco laboris nisi ut aliquip ex ea commodo consequat.</p>]]></value>
              </action>
              <action>
                  <action_id>set_metadata_field_wysiwyg_1693525114_description</action_id>
                  <action_type>set_attribute_value</action_type>
                  <asset>[[output://create_metadata_field_wysiwyg_1693525114.assetid]]</asset>
                  <attribute>description</attribute>
                  <value><![CDATA[]]></value>
              </action>
              <action>
                  <action_id>set_metadata_field_wysiwyg_1693525114_editable</action_id>
                  <action_type>set_attribute_value</action_type>
                  <asset>[[output://create_metadata_field_wysiwyg_1693525114.assetid]]</asset>
                  <attribute>editable</attribute>
                  <value><![CDATA[1]]></value>
              </action>
              <action>
                  <action_id>set_metadata_field_wysiwyg_1693525114_editable</action_id>
                  <action_type>set_attribute_value</action_type>
                  <asset>[[output://create_metadata_field_wysiwyg_1693525114.assetid]]</asset>
                  <attribute>editable</attribute>
                  <value><![CDATA[1]]></value>
              </action>
              <action>
                  <action_id>set_metadata_field_wysiwyg_1693525114_required</action_id>
                  <action_type>set_attribute_value</action_type>
                  <asset>[[output://create_metadata_field_wysiwyg_1693525114.assetid]]</asset>
                  <attribute>required</attribute>
                  <value><![CDATA[0]]></value>
              </action>
              <action>
                  <action_id>set_permission_1693525114_read_5</action_id>
                  <action_type>set_permission</action_type>
                  <asset>[[output://create_metadata_field_wysiwyg_1693525114.assetid]]</asset>
                  <permission>1</permission>
                  <granted>1</granted>
                  <userid>[[system://public_user]]</userid>
              </action>
              
              <action>
                  <action_id>create_metadata_field_related_asset_1136448972</action_id>
                  <action_type>create_asset</action_type>
                  <type_code>metadata_field_related_asset</type_code>
                  <link_type>2</link_type>
                  <parentid>[[output://create_Metadata_Section_912922464.assetid]]</parentid>
                  <value></value>
                  <is_dependant>1</is_dependant>
                  <is_exclusive>0</is_exclusive>
              </action> 
              <action>
                  <action_id>set_metadata_field_related_asset_1136448972_name</action_id>
                  <action_type>set_attribute_value</action_type>
                  <asset>[[output://create_metadata_field_related_asset_1136448972.assetid]]</asset>
                  <attribute>name</attribute>
                  <value><![CDATA[hero_image]]></value>
              </action>
              <action>
                  <action_id>set_metadata_field_related_asset_1136448972_friendly_name</action_id>
                  <action_type>set_attribute_value</action_type>
                  <asset>[[output://create_metadata_field_related_asset_1136448972.assetid]]</asset>
                  <attribute>friendly_name</attribute>
                  <value><![CDATA[Image]]></value>
              </action>
              <action>
                  <action_id>set_metadata_field_related_asset_1136448972_default</action_id>
                  <action_type>set_attribute_value</action_type>
                  <asset>[[output://create_metadata_field_related_asset_1136448972.assetid]]</asset>
                  <attribute>default</attribute>
                  <value><![CDATA[https://via.placeholder.com/782x520]]></value>
              </action>
              <action>
                  <action_id>set_metadata_field_related_asset_1136448972_description</action_id>
                  <action_type>set_attribute_value</action_type>
                  <asset>[[output://create_metadata_field_related_asset_1136448972.assetid]]</asset>
                  <attribute>description</attribute>
                  <value><![CDATA[]]></value>
              </action>
              <action>
                  <action_id>set_metadata_field_related_asset_1136448972_editable</action_id>
                  <action_type>set_attribute_value</action_type>
                  <asset>[[output://create_metadata_field_related_asset_1136448972.assetid]]</asset>
                  <attribute>editable</attribute>
                  <value><![CDATA[1]]></value>
              </action>
              <action>
                  <action_id>set_metadata_field_related_asset_1136448972_editable</action_id>
                  <action_type>set_attribute_value</action_type>
                  <asset>[[output://create_metadata_field_related_asset_1136448972.assetid]]</asset>
                  <attribute>editable</attribute>
                  <value><![CDATA[1]]></value>
              </action>
              <action>
                  <action_id>set_metadata_field_related_asset_1136448972_required</action_id>
                  <action_type>set_attribute_value</action_type>
                  <asset>[[output://create_metadata_field_related_asset_1136448972.assetid]]</asset>
                  <attribute>required</attribute>
                  <value><![CDATA[0]]></value>
              </action>
              <action>
                  <action_id>set_permission_1136448972_read_5</action_id>
                  <action_type>set_permission</action_type>
                  <asset>[[output://create_metadata_field_related_asset_1136448972.assetid]]</asset>
                  <permission>1</permission>
                  <granted>1</granted>
                  <userid>[[system://public_user]]</userid>
              </action>
              
              <action>
                  <action_id>create_metadata_field_select_1666784421</action_id>
                  <action_type>create_asset</action_type>
                  <type_code>metadata_field_select</type_code>
                  <link_type>2</link_type>
                  <parentid>[[output://create_Metadata_Section_912922464.assetid]]</parentid>
                  <value></value>
                  <is_dependant>1</is_dependant>
                  <is_exclusive>0</is_exclusive>
              </action> 
              <action>
                  <action_id>set_metadata_field_select_1666784421_name</action_id>
                  <action_type>set_attribute_value</action_type>
                  <asset>[[output://create_metadata_field_select_1666784421.assetid]]</asset>
                  <attribute>name</attribute>
                  <value><![CDATA[hero_image_responsive_treatment]]></value>
              </action>
              <action>
                  <action_id>set_metadata_field_select_1666784421_friendly_name</action_id>
                  <action_type>set_attribute_value</action_type>
                  <asset>[[output://create_metadata_field_select_1666784421.assetid]]</asset>
                  <attribute>friendly_name</attribute>
                  <value><![CDATA[Responsive treatment]]></value>
              </action>
              <action>
                  <action_id>set_metadata_field_select_1666784421_default</action_id>
                  <action_type>set_attribute_value</action_type>
                  <asset>[[output://create_metadata_field_select_1666784421.assetid]]</asset>
                  <attribute>default</attribute>
                  <value><![CDATA[crop]]></value>
              </action>
              <action>
                  <action_id>set_metadata_field_select_1666784421_description</action_id>
                  <action_type>set_attribute_value</action_type>
                  <asset>[[output://create_metadata_field_select_1666784421.assetid]]</asset>
                  <attribute>description</attribute>
                  <value><![CDATA[]]></value>
              </action>
              <action>
                  <action_id>set_metadata_field_select_1666784421_editable</action_id>
                  <action_type>set_attribute_value</action_type>
                  <asset>[[output://create_metadata_field_select_1666784421.assetid]]</asset>
                  <attribute>editable</attribute>
                  <value><![CDATA[1]]></value>
              </action>
              <action>
                  <action_id>set_metadata_field_select_1666784421_editable</action_id>
                  <action_type>set_attribute_value</action_type>
                  <asset>[[output://create_metadata_field_select_1666784421.assetid]]</asset>
                  <attribute>editable</attribute>
                  <value><![CDATA[1]]></value>
              </action>
              <action>
                  <action_id>set_metadata_field_select_1666784421_required</action_id>
                  <action_type>set_attribute_value</action_type>
                  <asset>[[output://create_metadata_field_select_1666784421.assetid]]</asset>
                  <attribute>required</attribute>
                  <value><![CDATA[0]]></value>
              </action>
              <action>
                  <action_id>set_permission_1666784421_read_5</action_id>
                  <action_type>set_permission</action_type>
                  <asset>[[output://create_metadata_field_select_1666784421.assetid]]</asset>
                  <permission>1</permission>
                  <granted>1</granted>
                  <userid>[[system://public_user]]</userid>
              </action>
              
                  <action>
                      <action_id>set_metadata_field_select_1666784421_select_options</action_id>
                      <action_type>set_attribute_value</action_type>
                      <asset>[[output://create_metadata_field_select_1666784421.assetid]]</asset>
                      <attribute>select_options</attribute>
                      <value><![CDATA[array ('crop' => 'Crop','scale' => 'Scale',);]]></value>
                  </action>
                  <action>
                      <action_id>set_{f.type}_1666784421_edit_params</action_id>
                      <action_type>set_attribute_value</action_type>
                      <asset>[[output://create_metadata_field_select_1666784421.assetid]]</asset>
                      <attribute>edit_params</attribute>
                      <value><![CDATA[array (
                      'style' => 'list',
                      'type' => 'table',
                      'height' => '',
                      'columns' => '1',
                      'empty_text' => '',
                      'extras' => '',
                      );]]></value>
                  </action>  
                  
              <action>
                  <action_id>create_metadata_field_select_2922311413</action_id>
                  <action_type>create_asset</action_type>
                  <type_code>metadata_field_select</type_code>
                  <link_type>2</link_type>
                  <parentid>[[output://create_Metadata_Section_912922464.assetid]]</parentid>
                  <value></value>
                  <is_dependant>1</is_dependant>
                  <is_exclusive>0</is_exclusive>
              </action> 
              <action>
                  <action_id>set_metadata_field_select_2922311413_name</action_id>
                  <action_type>set_attribute_value</action_type>
                  <asset>[[output://create_metadata_field_select_2922311413.assetid]]</asset>
                  <attribute>name</attribute>
                  <value><![CDATA[hero_image_padding]]></value>
              </action>
              <action>
                  <action_id>set_metadata_field_select_2922311413_friendly_name</action_id>
                  <action_type>set_attribute_value</action_type>
                  <asset>[[output://create_metadata_field_select_2922311413.assetid]]</asset>
                  <attribute>friendly_name</attribute>
                  <value><![CDATA[Display Padding?]]></value>
              </action>
              <action>
                  <action_id>set_metadata_field_select_2922311413_default</action_id>
                  <action_type>set_attribute_value</action_type>
                  <asset>[[output://create_metadata_field_select_2922311413.assetid]]</asset>
                  <attribute>default</attribute>
                  <value><![CDATA[no]]></value>
              </action>
              <action>
                  <action_id>set_metadata_field_select_2922311413_description</action_id>
                  <action_type>set_attribute_value</action_type>
                  <asset>[[output://create_metadata_field_select_2922311413.assetid]]</asset>
                  <attribute>description</attribute>
                  <value><![CDATA[]]></value>
              </action>
              <action>
                  <action_id>set_metadata_field_select_2922311413_editable</action_id>
                  <action_type>set_attribute_value</action_type>
                  <asset>[[output://create_metadata_field_select_2922311413.assetid]]</asset>
                  <attribute>editable</attribute>
                  <value><![CDATA[1]]></value>
              </action>
              <action>
                  <action_id>set_metadata_field_select_2922311413_editable</action_id>
                  <action_type>set_attribute_value</action_type>
                  <asset>[[output://create_metadata_field_select_2922311413.assetid]]</asset>
                  <attribute>editable</attribute>
                  <value><![CDATA[1]]></value>
              </action>
              <action>
                  <action_id>set_metadata_field_select_2922311413_required</action_id>
                  <action_type>set_attribute_value</action_type>
                  <asset>[[output://create_metadata_field_select_2922311413.assetid]]</asset>
                  <attribute>required</attribute>
                  <value><![CDATA[0]]></value>
              </action>
              <action>
                  <action_id>set_permission_2922311413_read_5</action_id>
                  <action_type>set_permission</action_type>
                  <asset>[[output://create_metadata_field_select_2922311413.assetid]]</asset>
                  <permission>1</permission>
                  <granted>1</granted>
                  <userid>[[system://public_user]]</userid>
              </action>
              
                  <action>
                      <action_id>set_metadata_field_select_2922311413_select_options</action_id>
                      <action_type>set_attribute_value</action_type>
                      <asset>[[output://create_metadata_field_select_2922311413.assetid]]</asset>
                      <attribute>select_options</attribute>
                      <value><![CDATA[array ('no' => 'No','yes' => 'Yes',);]]></value>
                  </action>
                  <action>
                      <action_id>set_{f.type}_2922311413_edit_params</action_id>
                      <action_type>set_attribute_value</action_type>
                      <asset>[[output://create_metadata_field_select_2922311413.assetid]]</asset>
                      <attribute>edit_params</attribute>
                      <value><![CDATA[array (
                      'style' => 'list',
                      'type' => 'table',
                      'height' => '',
                      'columns' => '1',
                      'empty_text' => '',
                      'extras' => '',
                      );]]></value>
                  </action>  
                  
              <action>
                  <action_id>create_metadata_field_select_1933309217</action_id>
                  <action_type>create_asset</action_type>
                  <type_code>metadata_field_select</type_code>
                  <link_type>2</link_type>
                  <parentid>[[output://create_Metadata_Section_912922464.assetid]]</parentid>
                  <value></value>
                  <is_dependant>1</is_dependant>
                  <is_exclusive>0</is_exclusive>
              </action> 
              <action>
                  <action_id>set_metadata_field_select_1933309217_name</action_id>
                  <action_type>set_attribute_value</action_type>
                  <asset>[[output://create_metadata_field_select_1933309217.assetid]]</asset>
                  <attribute>name</attribute>
                  <value><![CDATA[background_type]]></value>
              </action>
              <action>
                  <action_id>set_metadata_field_select_1933309217_friendly_name</action_id>
                  <action_type>set_attribute_value</action_type>
                  <asset>[[output://create_metadata_field_select_1933309217.assetid]]</asset>
                  <attribute>friendly_name</attribute>
                  <value><![CDATA[Background type]]></value>
              </action>
              <action>
                  <action_id>set_metadata_field_select_1933309217_default</action_id>
                  <action_type>set_attribute_value</action_type>
                  <asset>[[output://create_metadata_field_select_1933309217.assetid]]</asset>
                  <attribute>default</attribute>
                  <value><![CDATA[image]]></value>
              </action>
              <action>
                  <action_id>set_metadata_field_select_1933309217_description</action_id>
                  <action_type>set_attribute_value</action_type>
                  <asset>[[output://create_metadata_field_select_1933309217.assetid]]</asset>
                  <attribute>description</attribute>
                  <value><![CDATA[]]></value>
              </action>
              <action>
                  <action_id>set_metadata_field_select_1933309217_editable</action_id>
                  <action_type>set_attribute_value</action_type>
                  <asset>[[output://create_metadata_field_select_1933309217.assetid]]</asset>
                  <attribute>editable</attribute>
                  <value><![CDATA[1]]></value>
              </action>
              <action>
                  <action_id>set_metadata_field_select_1933309217_editable</action_id>
                  <action_type>set_attribute_value</action_type>
                  <asset>[[output://create_metadata_field_select_1933309217.assetid]]</asset>
                  <attribute>editable</attribute>
                  <value><![CDATA[1]]></value>
              </action>
              <action>
                  <action_id>set_metadata_field_select_1933309217_required</action_id>
                  <action_type>set_attribute_value</action_type>
                  <asset>[[output://create_metadata_field_select_1933309217.assetid]]</asset>
                  <attribute>required</attribute>
                  <value><![CDATA[0]]></value>
              </action>
              <action>
                  <action_id>set_permission_1933309217_read_5</action_id>
                  <action_type>set_permission</action_type>
                  <asset>[[output://create_metadata_field_select_1933309217.assetid]]</asset>
                  <permission>1</permission>
                  <granted>1</granted>
                  <userid>[[system://public_user]]</userid>
              </action>
              
                  <action>
                      <action_id>set_metadata_field_select_1933309217_select_options</action_id>
                      <action_type>set_attribute_value</action_type>
                      <asset>[[output://create_metadata_field_select_1933309217.assetid]]</asset>
                      <attribute>select_options</attribute>
                      <value><![CDATA[array ('colour' => 'Colour','texture' => 'Texture','image' => 'Background Image',);]]></value>
                  </action>
                  <action>
                      <action_id>set_{f.type}_1933309217_edit_params</action_id>
                      <action_type>set_attribute_value</action_type>
                      <asset>[[output://create_metadata_field_select_1933309217.assetid]]</asset>
                      <attribute>edit_params</attribute>
                      <value><![CDATA[array (
                      'style' => 'list',
                      'type' => 'table',
                      'height' => '',
                      'columns' => '1',
                      'empty_text' => '',
                      'extras' => '',
                      );]]></value>
                  </action>  
                  
              <action>
                  <action_id>create_metadata_field_select_7842872978</action_id>
                  <action_type>create_asset</action_type>
                  <type_code>metadata_field_select</type_code>
                  <link_type>2</link_type>
                  <parentid>[[output://create_Metadata_Section_912922464.assetid]]</parentid>
                  <value></value>
                  <is_dependant>1</is_dependant>
                  <is_exclusive>0</is_exclusive>
              </action> 
              <action>
                  <action_id>set_metadata_field_select_7842872978_name</action_id>
                  <action_type>set_attribute_value</action_type>
                  <asset>[[output://create_metadata_field_select_7842872978.assetid]]</asset>
                  <attribute>name</attribute>
                  <value><![CDATA[background_colour]]></value>
              </action>
              <action>
                  <action_id>set_metadata_field_select_7842872978_friendly_name</action_id>
                  <action_type>set_attribute_value</action_type>
                  <asset>[[output://create_metadata_field_select_7842872978.assetid]]</asset>
                  <attribute>friendly_name</attribute>
                  <value><![CDATA[Background Colour]]></value>
              </action>
              <action>
                  <action_id>set_metadata_field_select_7842872978_default</action_id>
                  <action_type>set_attribute_value</action_type>
                  <asset>[[output://create_metadata_field_select_7842872978.assetid]]</asset>
                  <attribute>default</attribute>
                  <value><![CDATA[dark]]></value>
              </action>
              <action>
                  <action_id>set_metadata_field_select_7842872978_description</action_id>
                  <action_type>set_attribute_value</action_type>
                  <asset>[[output://create_metadata_field_select_7842872978.assetid]]</asset>
                  <attribute>description</attribute>
                  <value><![CDATA[]]></value>
              </action>
              <action>
                  <action_id>set_metadata_field_select_7842872978_editable</action_id>
                  <action_type>set_attribute_value</action_type>
                  <asset>[[output://create_metadata_field_select_7842872978.assetid]]</asset>
                  <attribute>editable</attribute>
                  <value><![CDATA[1]]></value>
              </action>
              <action>
                  <action_id>set_metadata_field_select_7842872978_editable</action_id>
                  <action_type>set_attribute_value</action_type>
                  <asset>[[output://create_metadata_field_select_7842872978.assetid]]</asset>
                  <attribute>editable</attribute>
                  <value><![CDATA[1]]></value>
              </action>
              <action>
                  <action_id>set_metadata_field_select_7842872978_required</action_id>
                  <action_type>set_attribute_value</action_type>
                  <asset>[[output://create_metadata_field_select_7842872978.assetid]]</asset>
                  <attribute>required</attribute>
                  <value><![CDATA[0]]></value>
              </action>
              <action>
                  <action_id>set_permission_7842872978_read_5</action_id>
                  <action_type>set_permission</action_type>
                  <asset>[[output://create_metadata_field_select_7842872978.assetid]]</asset>
                  <permission>1</permission>
                  <granted>1</granted>
                  <userid>[[system://public_user]]</userid>
              </action>
              
                  <action>
                      <action_id>set_metadata_field_select_7842872978_select_options</action_id>
                      <action_type>set_attribute_value</action_type>
                      <asset>[[output://create_metadata_field_select_7842872978.assetid]]</asset>
                      <attribute>select_options</attribute>
                      <value><![CDATA[array ('' => 'White','light' => 'Light','alternate' => 'Alternate','dark' => 'Dark','dark-alternate' => 'Dark Alternate',);]]></value>
                  </action>
                  <action>
                      <action_id>set_{f.type}_7842872978_edit_params</action_id>
                      <action_type>set_attribute_value</action_type>
                      <asset>[[output://create_metadata_field_select_7842872978.assetid]]</asset>
                      <attribute>edit_params</attribute>
                      <value><![CDATA[array (
                      'style' => 'list',
                      'type' => 'table',
                      'height' => '',
                      'columns' => '1',
                      'empty_text' => '',
                      'extras' => '',
                      );]]></value>
                  </action>  
                  
              <action>
                  <action_id>create_metadata_field_related_asset_6535687888</action_id>
                  <action_type>create_asset</action_type>
                  <type_code>metadata_field_related_asset</type_code>
                  <link_type>2</link_type>
                  <parentid>[[output://create_Metadata_Section_912922464.assetid]]</parentid>
                  <value></value>
                  <is_dependant>1</is_dependant>
                  <is_exclusive>0</is_exclusive>
              </action> 
              <action>
                  <action_id>set_metadata_field_related_asset_6535687888_name</action_id>
                  <action_type>set_attribute_value</action_type>
                  <asset>[[output://create_metadata_field_related_asset_6535687888.assetid]]</asset>
                  <attribute>name</attribute>
                  <value><![CDATA[background_image_sm]]></value>
              </action>
              <action>
                  <action_id>set_metadata_field_related_asset_6535687888_friendly_name</action_id>
                  <action_type>set_attribute_value</action_type>
                  <asset>[[output://create_metadata_field_related_asset_6535687888.assetid]]</asset>
                  <attribute>friendly_name</attribute>
                  <value><![CDATA[Background Image - Mobile]]></value>
              </action>
              <action>
                  <action_id>set_metadata_field_related_asset_6535687888_default</action_id>
                  <action_type>set_attribute_value</action_type>
                  <asset>[[output://create_metadata_field_related_asset_6535687888.assetid]]</asset>
                  <attribute>default</attribute>
                  <value><![CDATA[/mysource_files/banner-bg.png]]></value>
              </action>
              <action>
                  <action_id>set_metadata_field_related_asset_6535687888_description</action_id>
                  <action_type>set_attribute_value</action_type>
                  <asset>[[output://create_metadata_field_related_asset_6535687888.assetid]]</asset>
                  <attribute>description</attribute>
                  <value><![CDATA[]]></value>
              </action>
              <action>
                  <action_id>set_metadata_field_related_asset_6535687888_editable</action_id>
                  <action_type>set_attribute_value</action_type>
                  <asset>[[output://create_metadata_field_related_asset_6535687888.assetid]]</asset>
                  <attribute>editable</attribute>
                  <value><![CDATA[1]]></value>
              </action>
              <action>
                  <action_id>set_metadata_field_related_asset_6535687888_editable</action_id>
                  <action_type>set_attribute_value</action_type>
                  <asset>[[output://create_metadata_field_related_asset_6535687888.assetid]]</asset>
                  <attribute>editable</attribute>
                  <value><![CDATA[1]]></value>
              </action>
              <action>
                  <action_id>set_metadata_field_related_asset_6535687888_required</action_id>
                  <action_type>set_attribute_value</action_type>
                  <asset>[[output://create_metadata_field_related_asset_6535687888.assetid]]</asset>
                  <attribute>required</attribute>
                  <value><![CDATA[0]]></value>
              </action>
              <action>
                  <action_id>set_permission_6535687888_read_5</action_id>
                  <action_type>set_permission</action_type>
                  <asset>[[output://create_metadata_field_related_asset_6535687888.assetid]]</asset>
                  <permission>1</permission>
                  <granted>1</granted>
                  <userid>[[system://public_user]]</userid>
              </action>
              
              <action>
                  <action_id>create_metadata_field_related_asset_4228336828</action_id>
                  <action_type>create_asset</action_type>
                  <type_code>metadata_field_related_asset</type_code>
                  <link_type>2</link_type>
                  <parentid>[[output://create_Metadata_Section_912922464.assetid]]</parentid>
                  <value></value>
                  <is_dependant>1</is_dependant>
                  <is_exclusive>0</is_exclusive>
              </action> 
              <action>
                  <action_id>set_metadata_field_related_asset_4228336828_name</action_id>
                  <action_type>set_attribute_value</action_type>
                  <asset>[[output://create_metadata_field_related_asset_4228336828.assetid]]</asset>
                  <attribute>name</attribute>
                  <value><![CDATA[background_image_lg]]></value>
              </action>
              <action>
                  <action_id>set_metadata_field_related_asset_4228336828_friendly_name</action_id>
                  <action_type>set_attribute_value</action_type>
                  <asset>[[output://create_metadata_field_related_asset_4228336828.assetid]]</asset>
                  <attribute>friendly_name</attribute>
                  <value><![CDATA[Background Image - Desktop and Tablet]]></value>
              </action>
              <action>
                  <action_id>set_metadata_field_related_asset_4228336828_default</action_id>
                  <action_type>set_attribute_value</action_type>
                  <asset>[[output://create_metadata_field_related_asset_4228336828.assetid]]</asset>
                  <attribute>default</attribute>
                  <value><![CDATA[/mysource_files/banner-bg.png]]></value>
              </action>
              <action>
                  <action_id>set_metadata_field_related_asset_4228336828_description</action_id>
                  <action_type>set_attribute_value</action_type>
                  <asset>[[output://create_metadata_field_related_asset_4228336828.assetid]]</asset>
                  <attribute>description</attribute>
                  <value><![CDATA[]]></value>
              </action>
              <action>
                  <action_id>set_metadata_field_related_asset_4228336828_editable</action_id>
                  <action_type>set_attribute_value</action_type>
                  <asset>[[output://create_metadata_field_related_asset_4228336828.assetid]]</asset>
                  <attribute>editable</attribute>
                  <value><![CDATA[1]]></value>
              </action>
              <action>
                  <action_id>set_metadata_field_related_asset_4228336828_editable</action_id>
                  <action_type>set_attribute_value</action_type>
                  <asset>[[output://create_metadata_field_related_asset_4228336828.assetid]]</asset>
                  <attribute>editable</attribute>
                  <value><![CDATA[1]]></value>
              </action>
              <action>
                  <action_id>set_metadata_field_related_asset_4228336828_required</action_id>
                  <action_type>set_attribute_value</action_type>
                  <asset>[[output://create_metadata_field_related_asset_4228336828.assetid]]</asset>
                  <attribute>required</attribute>
                  <value><![CDATA[0]]></value>
              </action>
              <action>
                  <action_id>set_permission_4228336828_read_5</action_id>
                  <action_type>set_permission</action_type>
                  <asset>[[output://create_metadata_field_related_asset_4228336828.assetid]]</asset>
                  <permission>1</permission>
                  <granted>1</granted>
                  <userid>[[system://public_user]]</userid>
              </action>
              
              <action>
                  <action_id>create_metadata_field_select_425355143</action_id>
                  <action_type>create_asset</action_type>
                  <type_code>metadata_field_select</type_code>
                  <link_type>2</link_type>
                  <parentid>[[output://create_Metadata_Section_912922464.assetid]]</parentid>
                  <value></value>
                  <is_dependant>1</is_dependant>
                  <is_exclusive>0</is_exclusive>
              </action> 
              <action>
                  <action_id>set_metadata_field_select_425355143_name</action_id>
                  <action_type>set_attribute_value</action_type>
                  <asset>[[output://create_metadata_field_select_425355143.assetid]]</asset>
                  <attribute>name</attribute>
                  <value><![CDATA[background_image_alignment]]></value>
              </action>
              <action>
                  <action_id>set_metadata_field_select_425355143_friendly_name</action_id>
                  <action_type>set_attribute_value</action_type>
                  <asset>[[output://create_metadata_field_select_425355143.assetid]]</asset>
                  <attribute>friendly_name</attribute>
                  <value><![CDATA[Background alignment]]></value>
              </action>
              <action>
                  <action_id>set_metadata_field_select_425355143_default</action_id>
                  <action_type>set_attribute_value</action_type>
                  <asset>[[output://create_metadata_field_select_425355143.assetid]]</asset>
                  <attribute>default</attribute>
                  <value><![CDATA[center]]></value>
              </action>
              <action>
                  <action_id>set_metadata_field_select_425355143_description</action_id>
                  <action_type>set_attribute_value</action_type>
                  <asset>[[output://create_metadata_field_select_425355143.assetid]]</asset>
                  <attribute>description</attribute>
                  <value><![CDATA[]]></value>
              </action>
              <action>
                  <action_id>set_metadata_field_select_425355143_editable</action_id>
                  <action_type>set_attribute_value</action_type>
                  <asset>[[output://create_metadata_field_select_425355143.assetid]]</asset>
                  <attribute>editable</attribute>
                  <value><![CDATA[1]]></value>
              </action>
              <action>
                  <action_id>set_metadata_field_select_425355143_editable</action_id>
                  <action_type>set_attribute_value</action_type>
                  <asset>[[output://create_metadata_field_select_425355143.assetid]]</asset>
                  <attribute>editable</attribute>
                  <value><![CDATA[1]]></value>
              </action>
              <action>
                  <action_id>set_metadata_field_select_425355143_required</action_id>
                  <action_type>set_attribute_value</action_type>
                  <asset>[[output://create_metadata_field_select_425355143.assetid]]</asset>
                  <attribute>required</attribute>
                  <value><![CDATA[0]]></value>
              </action>
              <action>
                  <action_id>set_permission_425355143_read_5</action_id>
                  <action_type>set_permission</action_type>
                  <asset>[[output://create_metadata_field_select_425355143.assetid]]</asset>
                  <permission>1</permission>
                  <granted>1</granted>
                  <userid>[[system://public_user]]</userid>
              </action>
              
                  <action>
                      <action_id>set_metadata_field_select_425355143_select_options</action_id>
                      <action_type>set_attribute_value</action_type>
                      <asset>[[output://create_metadata_field_select_425355143.assetid]]</asset>
                      <attribute>select_options</attribute>
                      <value><![CDATA[array ('left' => 'Left','right' => 'Right','center' => 'Center',);]]></value>
                  </action>
                  <action>
                      <action_id>set_{f.type}_425355143_edit_params</action_id>
                      <action_type>set_attribute_value</action_type>
                      <asset>[[output://create_metadata_field_select_425355143.assetid]]</asset>
                      <attribute>edit_params</attribute>
                      <value><![CDATA[array (
                      'style' => 'list',
                      'type' => 'table',
                      'height' => '',
                      'columns' => '1',
                      'empty_text' => '',
                      'extras' => '',
                      );]]></value>
                  </action>  
                  
              <action>
                  <action_id>create_metadata_field_text_9643088057</action_id>
                  <action_type>create_asset</action_type>
                  <type_code>metadata_field_text</type_code>
                  <link_type>2</link_type>
                  <parentid>[[output://create_Metadata_Section_912922464.assetid]]</parentid>
                  <value></value>
                  <is_dependant>1</is_dependant>
                  <is_exclusive>0</is_exclusive>
              </action> 
              <action>
                  <action_id>set_metadata_field_text_9643088057_name</action_id>
                  <action_type>set_attribute_value</action_type>
                  <asset>[[output://create_metadata_field_text_9643088057.assetid]]</asset>
                  <attribute>name</attribute>
                  <value><![CDATA[cta_button_primary_text]]></value>
              </action>
              <action>
                  <action_id>set_metadata_field_text_9643088057_friendly_name</action_id>
                  <action_type>set_attribute_value</action_type>
                  <asset>[[output://create_metadata_field_text_9643088057.assetid]]</asset>
                  <attribute>friendly_name</attribute>
                  <value><![CDATA[Primary Button Text]]></value>
              </action>
              <action>
                  <action_id>set_metadata_field_text_9643088057_default</action_id>
                  <action_type>set_attribute_value</action_type>
                  <asset>[[output://create_metadata_field_text_9643088057.assetid]]</asset>
                  <attribute>default</attribute>
                  <value><![CDATA[Primary Button]]></value>
              </action>
              <action>
                  <action_id>set_metadata_field_text_9643088057_description</action_id>
                  <action_type>set_attribute_value</action_type>
                  <asset>[[output://create_metadata_field_text_9643088057.assetid]]</asset>
                  <attribute>description</attribute>
                  <value><![CDATA[]]></value>
              </action>
              <action>
                  <action_id>set_metadata_field_text_9643088057_editable</action_id>
                  <action_type>set_attribute_value</action_type>
                  <asset>[[output://create_metadata_field_text_9643088057.assetid]]</asset>
                  <attribute>editable</attribute>
                  <value><![CDATA[1]]></value>
              </action>
              <action>
                  <action_id>set_metadata_field_text_9643088057_editable</action_id>
                  <action_type>set_attribute_value</action_type>
                  <asset>[[output://create_metadata_field_text_9643088057.assetid]]</asset>
                  <attribute>editable</attribute>
                  <value><![CDATA[1]]></value>
              </action>
              <action>
                  <action_id>set_metadata_field_text_9643088057_required</action_id>
                  <action_type>set_attribute_value</action_type>
                  <asset>[[output://create_metadata_field_text_9643088057.assetid]]</asset>
                  <attribute>required</attribute>
                  <value><![CDATA[0]]></value>
              </action>
              <action>
                  <action_id>set_permission_9643088057_read_5</action_id>
                  <action_type>set_permission</action_type>
                  <asset>[[output://create_metadata_field_text_9643088057.assetid]]</asset>
                  <permission>1</permission>
                  <granted>1</granted>
                  <userid>[[system://public_user]]</userid>
              </action>
              
              <action>
                  <action_id>create_metadata_field_related_asset_1442149695</action_id>
                  <action_type>create_asset</action_type>
                  <type_code>metadata_field_related_asset</type_code>
                  <link_type>2</link_type>
                  <parentid>[[output://create_Metadata_Section_912922464.assetid]]</parentid>
                  <value></value>
                  <is_dependant>1</is_dependant>
                  <is_exclusive>0</is_exclusive>
              </action> 
              <action>
                  <action_id>set_metadata_field_related_asset_1442149695_name</action_id>
                  <action_type>set_attribute_value</action_type>
                  <asset>[[output://create_metadata_field_related_asset_1442149695.assetid]]</asset>
                  <attribute>name</attribute>
                  <value><![CDATA[cta_button_primary_link]]></value>
              </action>
              <action>
                  <action_id>set_metadata_field_related_asset_1442149695_friendly_name</action_id>
                  <action_type>set_attribute_value</action_type>
                  <asset>[[output://create_metadata_field_related_asset_1442149695.assetid]]</asset>
                  <attribute>friendly_name</attribute>
                  <value><![CDATA[Primary Button Link]]></value>
              </action>
              <action>
                  <action_id>set_metadata_field_related_asset_1442149695_default</action_id>
                  <action_type>set_attribute_value</action_type>
                  <asset>[[output://create_metadata_field_related_asset_1442149695.assetid]]</asset>
                  <attribute>default</attribute>
                  <value><![CDATA[#]]></value>
              </action>
              <action>
                  <action_id>set_metadata_field_related_asset_1442149695_description</action_id>
                  <action_type>set_attribute_value</action_type>
                  <asset>[[output://create_metadata_field_related_asset_1442149695.assetid]]</asset>
                  <attribute>description</attribute>
                  <value><![CDATA[]]></value>
              </action>
              <action>
                  <action_id>set_metadata_field_related_asset_1442149695_editable</action_id>
                  <action_type>set_attribute_value</action_type>
                  <asset>[[output://create_metadata_field_related_asset_1442149695.assetid]]</asset>
                  <attribute>editable</attribute>
                  <value><![CDATA[1]]></value>
              </action>
              <action>
                  <action_id>set_metadata_field_related_asset_1442149695_editable</action_id>
                  <action_type>set_attribute_value</action_type>
                  <asset>[[output://create_metadata_field_related_asset_1442149695.assetid]]</asset>
                  <attribute>editable</attribute>
                  <value><![CDATA[1]]></value>
              </action>
              <action>
                  <action_id>set_metadata_field_related_asset_1442149695_required</action_id>
                  <action_type>set_attribute_value</action_type>
                  <asset>[[output://create_metadata_field_related_asset_1442149695.assetid]]</asset>
                  <attribute>required</attribute>
                  <value><![CDATA[0]]></value>
              </action>
              <action>
                  <action_id>set_permission_1442149695_read_5</action_id>
                  <action_type>set_permission</action_type>
                  <asset>[[output://create_metadata_field_related_asset_1442149695.assetid]]</asset>
                  <permission>1</permission>
                  <granted>1</granted>
                  <userid>[[system://public_user]]</userid>
              </action>
              
              <action>
                  <action_id>create_metadata_field_text_3555837316</action_id>
                  <action_type>create_asset</action_type>
                  <type_code>metadata_field_text</type_code>
                  <link_type>2</link_type>
                  <parentid>[[output://create_Metadata_Section_912922464.assetid]]</parentid>
                  <value></value>
                  <is_dependant>1</is_dependant>
                  <is_exclusive>0</is_exclusive>
              </action> 
              <action>
                  <action_id>set_metadata_field_text_3555837316_name</action_id>
                  <action_type>set_attribute_value</action_type>
                  <asset>[[output://create_metadata_field_text_3555837316.assetid]]</asset>
                  <attribute>name</attribute>
                  <value><![CDATA[cta_button_secondary_text]]></value>
              </action>
              <action>
                  <action_id>set_metadata_field_text_3555837316_friendly_name</action_id>
                  <action_type>set_attribute_value</action_type>
                  <asset>[[output://create_metadata_field_text_3555837316.assetid]]</asset>
                  <attribute>friendly_name</attribute>
                  <value><![CDATA[Secondary Button Text]]></value>
              </action>
              <action>
                  <action_id>set_metadata_field_text_3555837316_default</action_id>
                  <action_type>set_attribute_value</action_type>
                  <asset>[[output://create_metadata_field_text_3555837316.assetid]]</asset>
                  <attribute>default</attribute>
                  <value><![CDATA[Secondary Button]]></value>
              </action>
              <action>
                  <action_id>set_metadata_field_text_3555837316_description</action_id>
                  <action_type>set_attribute_value</action_type>
                  <asset>[[output://create_metadata_field_text_3555837316.assetid]]</asset>
                  <attribute>description</attribute>
                  <value><![CDATA[]]></value>
              </action>
              <action>
                  <action_id>set_metadata_field_text_3555837316_editable</action_id>
                  <action_type>set_attribute_value</action_type>
                  <asset>[[output://create_metadata_field_text_3555837316.assetid]]</asset>
                  <attribute>editable</attribute>
                  <value><![CDATA[1]]></value>
              </action>
              <action>
                  <action_id>set_metadata_field_text_3555837316_editable</action_id>
                  <action_type>set_attribute_value</action_type>
                  <asset>[[output://create_metadata_field_text_3555837316.assetid]]</asset>
                  <attribute>editable</attribute>
                  <value><![CDATA[1]]></value>
              </action>
              <action>
                  <action_id>set_metadata_field_text_3555837316_required</action_id>
                  <action_type>set_attribute_value</action_type>
                  <asset>[[output://create_metadata_field_text_3555837316.assetid]]</asset>
                  <attribute>required</attribute>
                  <value><![CDATA[0]]></value>
              </action>
              <action>
                  <action_id>set_permission_3555837316_read_5</action_id>
                  <action_type>set_permission</action_type>
                  <asset>[[output://create_metadata_field_text_3555837316.assetid]]</asset>
                  <permission>1</permission>
                  <granted>1</granted>
                  <userid>[[system://public_user]]</userid>
              </action>
              
              <action>
                  <action_id>create_metadata_field_related_asset_9441275067</action_id>
                  <action_type>create_asset</action_type>
                  <type_code>metadata_field_related_asset</type_code>
                  <link_type>2</link_type>
                  <parentid>[[output://create_Metadata_Section_912922464.assetid]]</parentid>
                  <value></value>
                  <is_dependant>1</is_dependant>
                  <is_exclusive>0</is_exclusive>
              </action> 
              <action>
                  <action_id>set_metadata_field_related_asset_9441275067_name</action_id>
                  <action_type>set_attribute_value</action_type>
                  <asset>[[output://create_metadata_field_related_asset_9441275067.assetid]]</asset>
                  <attribute>name</attribute>
                  <value><![CDATA[cta_button_secondary_link]]></value>
              </action>
              <action>
                  <action_id>set_metadata_field_related_asset_9441275067_friendly_name</action_id>
                  <action_type>set_attribute_value</action_type>
                  <asset>[[output://create_metadata_field_related_asset_9441275067.assetid]]</asset>
                  <attribute>friendly_name</attribute>
                  <value><![CDATA[Secondary Button Link]]></value>
              </action>
              <action>
                  <action_id>set_metadata_field_related_asset_9441275067_default</action_id>
                  <action_type>set_attribute_value</action_type>
                  <asset>[[output://create_metadata_field_related_asset_9441275067.assetid]]</asset>
                  <attribute>default</attribute>
                  <value><![CDATA[#]]></value>
              </action>
              <action>
                  <action_id>set_metadata_field_related_asset_9441275067_description</action_id>
                  <action_type>set_attribute_value</action_type>
                  <asset>[[output://create_metadata_field_related_asset_9441275067.assetid]]</asset>
                  <attribute>description</attribute>
                  <value><![CDATA[]]></value>
              </action>
              <action>
                  <action_id>set_metadata_field_related_asset_9441275067_editable</action_id>
                  <action_type>set_attribute_value</action_type>
                  <asset>[[output://create_metadata_field_related_asset_9441275067.assetid]]</asset>
                  <attribute>editable</attribute>
                  <value><![CDATA[1]]></value>
              </action>
              <action>
                  <action_id>set_metadata_field_related_asset_9441275067_editable</action_id>
                  <action_type>set_attribute_value</action_type>
                  <asset>[[output://create_metadata_field_related_asset_9441275067.assetid]]</asset>
                  <attribute>editable</attribute>
                  <value><![CDATA[1]]></value>
              </action>
              <action>
                  <action_id>set_metadata_field_related_asset_9441275067_required</action_id>
                  <action_type>set_attribute_value</action_type>
                  <asset>[[output://create_metadata_field_related_asset_9441275067.assetid]]</asset>
                  <attribute>required</attribute>
                  <value><![CDATA[0]]></value>
              </action>
              <action>
                  <action_id>set_permission_9441275067_read_5</action_id>
                  <action_type>set_permission</action_type>
                  <asset>[[output://create_metadata_field_related_asset_9441275067.assetid]]</asset>
                  <permission>1</permission>
                  <granted>1</granted>
                  <userid>[[system://public_user]]</userid>
              </action>
              
              <action>
                  <action_id>create_metadata_field_text_262019243</action_id>
                  <action_type>create_asset</action_type>
                  <type_code>metadata_field_text</type_code>
                  <link_type>2</link_type>
                  <parentid>[[output://create_Metadata_Section_912922464.assetid]]</parentid>
                  <value></value>
                  <is_dependant>1</is_dependant>
                  <is_exclusive>0</is_exclusive>
              </action> 
              <action>
                  <action_id>set_metadata_field_text_262019243_name</action_id>
                  <action_type>set_attribute_value</action_type>
                  <asset>[[output://create_metadata_field_text_262019243.assetid]]</asset>
                  <attribute>name</attribute>
                  <value><![CDATA[id_field]]></value>
              </action>
              <action>
                  <action_id>set_metadata_field_text_262019243_friendly_name</action_id>
                  <action_type>set_attribute_value</action_type>
                  <asset>[[output://create_metadata_field_text_262019243.assetid]]</asset>
                  <attribute>friendly_name</attribute>
                  <value><![CDATA[Id field]]></value>
              </action>
              <action>
                  <action_id>set_metadata_field_text_262019243_default</action_id>
                  <action_type>set_attribute_value</action_type>
                  <asset>[[output://create_metadata_field_text_262019243.assetid]]</asset>
                  <attribute>default</attribute>
                  <value><![CDATA[]]></value>
              </action>
              <action>
                  <action_id>set_metadata_field_text_262019243_description</action_id>
                  <action_type>set_attribute_value</action_type>
                  <asset>[[output://create_metadata_field_text_262019243.assetid]]</asset>
                  <attribute>description</attribute>
                  <value><![CDATA[]]></value>
              </action>
              <action>
                  <action_id>set_metadata_field_text_262019243_editable</action_id>
                  <action_type>set_attribute_value</action_type>
                  <asset>[[output://create_metadata_field_text_262019243.assetid]]</asset>
                  <attribute>editable</attribute>
                  <value><![CDATA[1]]></value>
              </action>
              <action>
                  <action_id>set_metadata_field_text_262019243_editable</action_id>
                  <action_type>set_attribute_value</action_type>
                  <asset>[[output://create_metadata_field_text_262019243.assetid]]</asset>
                  <attribute>editable</attribute>
                  <value><![CDATA[1]]></value>
              </action>
              <action>
                  <action_id>set_metadata_field_text_262019243_required</action_id>
                  <action_type>set_attribute_value</action_type>
                  <asset>[[output://create_metadata_field_text_262019243.assetid]]</asset>
                  <attribute>required</attribute>
                  <value><![CDATA[0]]></value>
              </action>
              <action>
                  <action_id>set_permission_262019243_read_5</action_id>
                  <action_type>set_permission</action_type>
                  <asset>[[output://create_metadata_field_text_262019243.assetid]]</asset>
                  <permission>1</permission>
                  <granted>1</granted>
                  <userid>[[system://public_user]]</userid>
              </action>
              </actions>