<?xml version="1.0" encoding="utf-8"?>
          <actions>
          <action>
            <action_id>create_Content_Container_Template_5608167870</action_id>
            <action_type>create_asset</action_type>
            <type_code>Content_Container_Template</type_code>
            <link_type>1</link_type>
            <parentid>1</parentid>
            <value></value>
            <is_dependant>0</is_dependant>
            <is_exclusive>0</is_exclusive>
          </action>
          <action>
            <action_id>set_Content_Container_Template_5608167870_name</action_id>
            <action_type>set_attribute_value</action_type>
            <asset>[[output://create_Content_Container_Template_5608167870.assetid]]</asset>
            <attribute>name</attribute>
            <value><![CDATA[Banner - Intermediate]]></value>
          </action>

          <action>
            <action_id>set_Content_Container_Template_5608167870_edit_interface_in_admin</action_id>
            <action_type>set_attribute_value</action_type>
            <asset>[[output://create_Content_Container_Template_5608167870.assetid]]</asset>
            <attribute>edit_interface_in_admin</attribute>
            <value><![CDATA[1]]></value>
          </action>

          <action>
            <action_id>set_Content_Container_Template_5608167870_icon_color</action_id>
            <action_type>set_attribute_value</action_type>
            <asset>[[output://create_Content_Container_Template_5608167870.assetid]]</asset>
            <attribute>icon_color</attribute>
            <value><![CDATA[blue]]></value>
          </action>
          
          <action>
          <action_id>create_Metadata_Schema_9203513132</action_id>
          <action_type>create_asset</action_type>
          <type_code>Metadata_Schema</type_code>
          <link_type>1</link_type>
          <parentid>[[output://create_Content_Container_Template_5608167870.assetid]]</parentid>
          <value></value>
          <is_dependant>0</is_dependant>
          <is_exclusive>0</is_exclusive>
          </action>
          <action>
            <action_id>set_Metadata_Schema_9203513132_name</action_id>
            <action_type>set_attribute_value</action_type>
            <asset>[[output://create_Metadata_Schema_9203513132.assetid]]</asset>
            <attribute>name</attribute>
            <value><![CDATA[Banner - Intermediate]]></value>
          </action>
          <action>
              <action_id>set_permission_9203513132_read_5</action_id>
              <action_type>set_permission</action_type>
              <asset>[[output://create_Metadata_Schema_9203513132.assetid]]</asset>
              <permission>1</permission>
              <granted>1</granted>
              <userid>[[system://public_user]]</userid>
          </action>
          
          <action>
            <action_id>create_Metadata_Section_8864946993</action_id>
            <action_type>create_asset</action_type>
            <type_code>Metadata_Section</type_code>
            <link_type>2</link_type>
            <parentid>[[output://create_Metadata_Schema_9203513132.assetid]]</parentid>
            <value></value>
            <is_dependant>1</is_dependant>
            <is_exclusive>0</is_exclusive>
          </action>
          <action>
            <action_id>add_Metadata_Section_8864946993_path</action_id>
            <action_type>add_web_path</action_type>
            <asset>[[output://create_Metadata_Section_8864946993.assetid]]</asset>
            <parent_asset>[[output://create_Metadata_Schema_9203513132.assetid]]</parent_asset>
            <path>settings</path>
          </action>
          <action>
            <action_id>set_Metadata_Section_8864946993_name</action_id>
            <action_type>set_attribute_value</action_type>
            <asset>[[output://create_Metadata_Section_8864946993.assetid]]</asset>
            <attribute>name</attribute>
            <value><![CDATA[Settings]]></value>
          </action>
          <action>
              <action_id>set_permission_8864946993_read_5</action_id>
              <action_type>set_permission</action_type>
              <asset>[[output://create_Metadata_Section_8864946993.assetid]]</asset>
              <permission>1</permission>
              <granted>1</granted>
              <userid>[[system://public_user]]</userid>
          </action>           
          
              <action>
                  <action_id>create_metadata_field_select_1004942733</action_id>
                  <action_type>create_asset</action_type>
                  <type_code>metadata_field_select</type_code>
                  <link_type>2</link_type>
                  <parentid>[[output://create_Metadata_Section_8864946993.assetid]]</parentid>
                  <value></value>
                  <is_dependant>1</is_dependant>
                  <is_exclusive>0</is_exclusive>
              </action> 
              <action>
                  <action_id>set_metadata_field_select_1004942733_name</action_id>
                  <action_type>set_attribute_value</action_type>
                  <asset>[[output://create_metadata_field_select_1004942733.assetid]]</asset>
                  <attribute>name</attribute>
                  <value><![CDATA[breadcrumbs_display]]></value>
              </action>
              <action>
                  <action_id>set_metadata_field_select_1004942733_friendly_name</action_id>
                  <action_type>set_attribute_value</action_type>
                  <asset>[[output://create_metadata_field_select_1004942733.assetid]]</asset>
                  <attribute>friendly_name</attribute>
                  <value><![CDATA[Display Breadcrumbs?]]></value>
              </action>
              <action>
                  <action_id>set_metadata_field_select_1004942733_default</action_id>
                  <action_type>set_attribute_value</action_type>
                  <asset>[[output://create_metadata_field_select_1004942733.assetid]]</asset>
                  <attribute>default</attribute>
                  <value><![CDATA[yes]]></value>
              </action>
              <action>
                  <action_id>set_metadata_field_select_1004942733_description</action_id>
                  <action_type>set_attribute_value</action_type>
                  <asset>[[output://create_metadata_field_select_1004942733.assetid]]</asset>
                  <attribute>description</attribute>
                  <value><![CDATA[]]></value>
              </action>
              <action>
                  <action_id>set_metadata_field_select_1004942733_editable</action_id>
                  <action_type>set_attribute_value</action_type>
                  <asset>[[output://create_metadata_field_select_1004942733.assetid]]</asset>
                  <attribute>editable</attribute>
                  <value><![CDATA[1]]></value>
              </action>
              <action>
                  <action_id>set_metadata_field_select_1004942733_editable</action_id>
                  <action_type>set_attribute_value</action_type>
                  <asset>[[output://create_metadata_field_select_1004942733.assetid]]</asset>
                  <attribute>editable</attribute>
                  <value><![CDATA[1]]></value>
              </action>
              <action>
                  <action_id>set_metadata_field_select_1004942733_required</action_id>
                  <action_type>set_attribute_value</action_type>
                  <asset>[[output://create_metadata_field_select_1004942733.assetid]]</asset>
                  <attribute>required</attribute>
                  <value><![CDATA[0]]></value>
              </action>
              <action>
                  <action_id>set_permission_1004942733_read_5</action_id>
                  <action_type>set_permission</action_type>
                  <asset>[[output://create_metadata_field_select_1004942733.assetid]]</asset>
                  <permission>1</permission>
                  <granted>1</granted>
                  <userid>[[system://public_user]]</userid>
              </action>
              
                  <action>
                      <action_id>set_metadata_field_select_1004942733_select_options</action_id>
                      <action_type>set_attribute_value</action_type>
                      <asset>[[output://create_metadata_field_select_1004942733.assetid]]</asset>
                      <attribute>select_options</attribute>
                      <value><![CDATA[array ('' => 'No','yes' => 'Yes',);]]></value>
                  </action>
                  <action>
                      <action_id>set_{f.type}_1004942733_edit_params</action_id>
                      <action_type>set_attribute_value</action_type>
                      <asset>[[output://create_metadata_field_select_1004942733.assetid]]</asset>
                      <attribute>edit_params</attribute>
                      <value><![CDATA[array (
                      'style' => 'list',
                      'type' => 'table',
                      'height' => '',
                      'columns' => '1',
                      'empty_text' => '',
                      'extras' => '',
                      );]]></value>
                  </action>  
                  
              <action>
                  <action_id>create_metadata_field_text_9488900944</action_id>
                  <action_type>create_asset</action_type>
                  <type_code>metadata_field_text</type_code>
                  <link_type>2</link_type>
                  <parentid>[[output://create_Metadata_Section_8864946993.assetid]]</parentid>
                  <value></value>
                  <is_dependant>1</is_dependant>
                  <is_exclusive>0</is_exclusive>
              </action> 
              <action>
                  <action_id>set_metadata_field_text_9488900944_name</action_id>
                  <action_type>set_attribute_value</action_type>
                  <asset>[[output://create_metadata_field_text_9488900944.assetid]]</asset>
                  <attribute>name</attribute>
                  <value><![CDATA[heading_primary]]></value>
              </action>
              <action>
                  <action_id>set_metadata_field_text_9488900944_friendly_name</action_id>
                  <action_type>set_attribute_value</action_type>
                  <asset>[[output://create_metadata_field_text_9488900944.assetid]]</asset>
                  <attribute>friendly_name</attribute>
                  <value><![CDATA[Primary Heading]]></value>
              </action>
              <action>
                  <action_id>set_metadata_field_text_9488900944_default</action_id>
                  <action_type>set_attribute_value</action_type>
                  <asset>[[output://create_metadata_field_text_9488900944.assetid]]</asset>
                  <attribute>default</attribute>
                  <value><![CDATA[Banner Intermediate]]></value>
              </action>
              <action>
                  <action_id>set_metadata_field_text_9488900944_description</action_id>
                  <action_type>set_attribute_value</action_type>
                  <asset>[[output://create_metadata_field_text_9488900944.assetid]]</asset>
                  <attribute>description</attribute>
                  <value><![CDATA[]]></value>
              </action>
              <action>
                  <action_id>set_metadata_field_text_9488900944_editable</action_id>
                  <action_type>set_attribute_value</action_type>
                  <asset>[[output://create_metadata_field_text_9488900944.assetid]]</asset>
                  <attribute>editable</attribute>
                  <value><![CDATA[1]]></value>
              </action>
              <action>
                  <action_id>set_metadata_field_text_9488900944_editable</action_id>
                  <action_type>set_attribute_value</action_type>
                  <asset>[[output://create_metadata_field_text_9488900944.assetid]]</asset>
                  <attribute>editable</attribute>
                  <value><![CDATA[1]]></value>
              </action>
              <action>
                  <action_id>set_metadata_field_text_9488900944_required</action_id>
                  <action_type>set_attribute_value</action_type>
                  <asset>[[output://create_metadata_field_text_9488900944.assetid]]</asset>
                  <attribute>required</attribute>
                  <value><![CDATA[0]]></value>
              </action>
              <action>
                  <action_id>set_permission_9488900944_read_5</action_id>
                  <action_type>set_permission</action_type>
                  <asset>[[output://create_metadata_field_text_9488900944.assetid]]</asset>
                  <permission>1</permission>
                  <granted>1</granted>
                  <userid>[[system://public_user]]</userid>
              </action>
              
              <action>
                  <action_id>create_metadata_field_text_3150130193</action_id>
                  <action_type>create_asset</action_type>
                  <type_code>metadata_field_text</type_code>
                  <link_type>2</link_type>
                  <parentid>[[output://create_Metadata_Section_8864946993.assetid]]</parentid>
                  <value></value>
                  <is_dependant>1</is_dependant>
                  <is_exclusive>0</is_exclusive>
              </action> 
              <action>
                  <action_id>set_metadata_field_text_3150130193_name</action_id>
                  <action_type>set_attribute_value</action_type>
                  <asset>[[output://create_metadata_field_text_3150130193.assetid]]</asset>
                  <attribute>name</attribute>
                  <value><![CDATA[heading_secondary]]></value>
              </action>
              <action>
                  <action_id>set_metadata_field_text_3150130193_friendly_name</action_id>
                  <action_type>set_attribute_value</action_type>
                  <asset>[[output://create_metadata_field_text_3150130193.assetid]]</asset>
                  <attribute>friendly_name</attribute>
                  <value><![CDATA[Secondary Heading]]></value>
              </action>
              <action>
                  <action_id>set_metadata_field_text_3150130193_default</action_id>
                  <action_type>set_attribute_value</action_type>
                  <asset>[[output://create_metadata_field_text_3150130193.assetid]]</asset>
                  <attribute>default</attribute>
                  <value><![CDATA[Heading Secondary]]></value>
              </action>
              <action>
                  <action_id>set_metadata_field_text_3150130193_description</action_id>
                  <action_type>set_attribute_value</action_type>
                  <asset>[[output://create_metadata_field_text_3150130193.assetid]]</asset>
                  <attribute>description</attribute>
                  <value><![CDATA[]]></value>
              </action>
              <action>
                  <action_id>set_metadata_field_text_3150130193_editable</action_id>
                  <action_type>set_attribute_value</action_type>
                  <asset>[[output://create_metadata_field_text_3150130193.assetid]]</asset>
                  <attribute>editable</attribute>
                  <value><![CDATA[1]]></value>
              </action>
              <action>
                  <action_id>set_metadata_field_text_3150130193_editable</action_id>
                  <action_type>set_attribute_value</action_type>
                  <asset>[[output://create_metadata_field_text_3150130193.assetid]]</asset>
                  <attribute>editable</attribute>
                  <value><![CDATA[1]]></value>
              </action>
              <action>
                  <action_id>set_metadata_field_text_3150130193_required</action_id>
                  <action_type>set_attribute_value</action_type>
                  <asset>[[output://create_metadata_field_text_3150130193.assetid]]</asset>
                  <attribute>required</attribute>
                  <value><![CDATA[0]]></value>
              </action>
              <action>
                  <action_id>set_permission_3150130193_read_5</action_id>
                  <action_type>set_permission</action_type>
                  <asset>[[output://create_metadata_field_text_3150130193.assetid]]</asset>
                  <permission>1</permission>
                  <granted>1</granted>
                  <userid>[[system://public_user]]</userid>
              </action>
              
              <action>
                  <action_id>create_metadata_field_select_2549513443</action_id>
                  <action_type>create_asset</action_type>
                  <type_code>metadata_field_select</type_code>
                  <link_type>2</link_type>
                  <parentid>[[output://create_Metadata_Section_8864946993.assetid]]</parentid>
                  <value></value>
                  <is_dependant>1</is_dependant>
                  <is_exclusive>0</is_exclusive>
              </action> 
              <action>
                  <action_id>set_metadata_field_select_2549513443_name</action_id>
                  <action_type>set_attribute_value</action_type>
                  <asset>[[output://create_metadata_field_select_2549513443.assetid]]</asset>
                  <attribute>name</attribute>
                  <value><![CDATA[heading_background_display]]></value>
              </action>
              <action>
                  <action_id>set_metadata_field_select_2549513443_friendly_name</action_id>
                  <action_type>set_attribute_value</action_type>
                  <asset>[[output://create_metadata_field_select_2549513443.assetid]]</asset>
                  <attribute>friendly_name</attribute>
                  <value><![CDATA[Display block background?]]></value>
              </action>
              <action>
                  <action_id>set_metadata_field_select_2549513443_default</action_id>
                  <action_type>set_attribute_value</action_type>
                  <asset>[[output://create_metadata_field_select_2549513443.assetid]]</asset>
                  <attribute>default</attribute>
                  <value><![CDATA[no]]></value>
              </action>
              <action>
                  <action_id>set_metadata_field_select_2549513443_description</action_id>
                  <action_type>set_attribute_value</action_type>
                  <asset>[[output://create_metadata_field_select_2549513443.assetid]]</asset>
                  <attribute>description</attribute>
                  <value><![CDATA[]]></value>
              </action>
              <action>
                  <action_id>set_metadata_field_select_2549513443_editable</action_id>
                  <action_type>set_attribute_value</action_type>
                  <asset>[[output://create_metadata_field_select_2549513443.assetid]]</asset>
                  <attribute>editable</attribute>
                  <value><![CDATA[1]]></value>
              </action>
              <action>
                  <action_id>set_metadata_field_select_2549513443_editable</action_id>
                  <action_type>set_attribute_value</action_type>
                  <asset>[[output://create_metadata_field_select_2549513443.assetid]]</asset>
                  <attribute>editable</attribute>
                  <value><![CDATA[1]]></value>
              </action>
              <action>
                  <action_id>set_metadata_field_select_2549513443_required</action_id>
                  <action_type>set_attribute_value</action_type>
                  <asset>[[output://create_metadata_field_select_2549513443.assetid]]</asset>
                  <attribute>required</attribute>
                  <value><![CDATA[0]]></value>
              </action>
              <action>
                  <action_id>set_permission_2549513443_read_5</action_id>
                  <action_type>set_permission</action_type>
                  <asset>[[output://create_metadata_field_select_2549513443.assetid]]</asset>
                  <permission>1</permission>
                  <granted>1</granted>
                  <userid>[[system://public_user]]</userid>
              </action>
              
                  <action>
                      <action_id>set_metadata_field_select_2549513443_select_options</action_id>
                      <action_type>set_attribute_value</action_type>
                      <asset>[[output://create_metadata_field_select_2549513443.assetid]]</asset>
                      <attribute>select_options</attribute>
                      <value><![CDATA[array ('' => 'No','yes' => 'Yes',);]]></value>
                  </action>
                  <action>
                      <action_id>set_{f.type}_2549513443_edit_params</action_id>
                      <action_type>set_attribute_value</action_type>
                      <asset>[[output://create_metadata_field_select_2549513443.assetid]]</asset>
                      <attribute>edit_params</attribute>
                      <value><![CDATA[array (
                      'style' => 'list',
                      'type' => 'table',
                      'height' => '',
                      'columns' => '1',
                      'empty_text' => '',
                      'extras' => '',
                      );]]></value>
                  </action>  
                  
              <action>
                  <action_id>create_metadata_field_wysiwyg_4869380506</action_id>
                  <action_type>create_asset</action_type>
                  <type_code>metadata_field_wysiwyg</type_code>
                  <link_type>2</link_type>
                  <parentid>[[output://create_Metadata_Section_8864946993.assetid]]</parentid>
                  <value></value>
                  <is_dependant>1</is_dependant>
                  <is_exclusive>0</is_exclusive>
              </action> 
              <action>
                  <action_id>set_metadata_field_wysiwyg_4869380506_name</action_id>
                  <action_type>set_attribute_value</action_type>
                  <asset>[[output://create_metadata_field_wysiwyg_4869380506.assetid]]</asset>
                  <attribute>name</attribute>
                  <value><![CDATA[abstract]]></value>
              </action>
              <action>
                  <action_id>set_metadata_field_wysiwyg_4869380506_friendly_name</action_id>
                  <action_type>set_attribute_value</action_type>
                  <asset>[[output://create_metadata_field_wysiwyg_4869380506.assetid]]</asset>
                  <attribute>friendly_name</attribute>
                  <value><![CDATA[Abstract]]></value>
              </action>
              <action>
                  <action_id>set_metadata_field_wysiwyg_4869380506_default</action_id>
                  <action_type>set_attribute_value</action_type>
                  <asset>[[output://create_metadata_field_wysiwyg_4869380506.assetid]]</asset>
                  <attribute>default</attribute>
                  <value><![CDATA[<p>Lorem ipsum dolor sit amet, consectetur adipiscing elit, sed do eiusmod tempor incididunt ut labore et dolore magna aliqua. Ut enim ad minim veniam, quis nostrud exercitation ullamco laboris nisi ut aliquip ex ea commodo consequat.</p>]]></value>
              </action>
              <action>
                  <action_id>set_metadata_field_wysiwyg_4869380506_description</action_id>
                  <action_type>set_attribute_value</action_type>
                  <asset>[[output://create_metadata_field_wysiwyg_4869380506.assetid]]</asset>
                  <attribute>description</attribute>
                  <value><![CDATA[]]></value>
              </action>
              <action>
                  <action_id>set_metadata_field_wysiwyg_4869380506_editable</action_id>
                  <action_type>set_attribute_value</action_type>
                  <asset>[[output://create_metadata_field_wysiwyg_4869380506.assetid]]</asset>
                  <attribute>editable</attribute>
                  <value><![CDATA[1]]></value>
              </action>
              <action>
                  <action_id>set_metadata_field_wysiwyg_4869380506_editable</action_id>
                  <action_type>set_attribute_value</action_type>
                  <asset>[[output://create_metadata_field_wysiwyg_4869380506.assetid]]</asset>
                  <attribute>editable</attribute>
                  <value><![CDATA[1]]></value>
              </action>
              <action>
                  <action_id>set_metadata_field_wysiwyg_4869380506_required</action_id>
                  <action_type>set_attribute_value</action_type>
                  <asset>[[output://create_metadata_field_wysiwyg_4869380506.assetid]]</asset>
                  <attribute>required</attribute>
                  <value><![CDATA[0]]></value>
              </action>
              <action>
                  <action_id>set_permission_4869380506_read_5</action_id>
                  <action_type>set_permission</action_type>
                  <asset>[[output://create_metadata_field_wysiwyg_4869380506.assetid]]</asset>
                  <permission>1</permission>
                  <granted>1</granted>
                  <userid>[[system://public_user]]</userid>
              </action>
              
              <action>
                  <action_id>create_metadata_field_related_asset_5460900916</action_id>
                  <action_type>create_asset</action_type>
                  <type_code>metadata_field_related_asset</type_code>
                  <link_type>2</link_type>
                  <parentid>[[output://create_Metadata_Section_8864946993.assetid]]</parentid>
                  <value></value>
                  <is_dependant>1</is_dependant>
                  <is_exclusive>0</is_exclusive>
              </action> 
              <action>
                  <action_id>set_metadata_field_related_asset_5460900916_name</action_id>
                  <action_type>set_attribute_value</action_type>
                  <asset>[[output://create_metadata_field_related_asset_5460900916.assetid]]</asset>
                  <attribute>name</attribute>
                  <value><![CDATA[hero_image]]></value>
              </action>
              <action>
                  <action_id>set_metadata_field_related_asset_5460900916_friendly_name</action_id>
                  <action_type>set_attribute_value</action_type>
                  <asset>[[output://create_metadata_field_related_asset_5460900916.assetid]]</asset>
                  <attribute>friendly_name</attribute>
                  <value><![CDATA[Image]]></value>
              </action>
              <action>
                  <action_id>set_metadata_field_related_asset_5460900916_default</action_id>
                  <action_type>set_attribute_value</action_type>
                  <asset>[[output://create_metadata_field_related_asset_5460900916.assetid]]</asset>
                  <attribute>default</attribute>
                  <value><![CDATA[https://via.placeholder.com/782x520]]></value>
              </action>
              <action>
                  <action_id>set_metadata_field_related_asset_5460900916_description</action_id>
                  <action_type>set_attribute_value</action_type>
                  <asset>[[output://create_metadata_field_related_asset_5460900916.assetid]]</asset>
                  <attribute>description</attribute>
                  <value><![CDATA[]]></value>
              </action>
              <action>
                  <action_id>set_metadata_field_related_asset_5460900916_editable</action_id>
                  <action_type>set_attribute_value</action_type>
                  <asset>[[output://create_metadata_field_related_asset_5460900916.assetid]]</asset>
                  <attribute>editable</attribute>
                  <value><![CDATA[1]]></value>
              </action>
              <action>
                  <action_id>set_metadata_field_related_asset_5460900916_editable</action_id>
                  <action_type>set_attribute_value</action_type>
                  <asset>[[output://create_metadata_field_related_asset_5460900916.assetid]]</asset>
                  <attribute>editable</attribute>
                  <value><![CDATA[1]]></value>
              </action>
              <action>
                  <action_id>set_metadata_field_related_asset_5460900916_required</action_id>
                  <action_type>set_attribute_value</action_type>
                  <asset>[[output://create_metadata_field_related_asset_5460900916.assetid]]</asset>
                  <attribute>required</attribute>
                  <value><![CDATA[0]]></value>
              </action>
              <action>
                  <action_id>set_permission_5460900916_read_5</action_id>
                  <action_type>set_permission</action_type>
                  <asset>[[output://create_metadata_field_related_asset_5460900916.assetid]]</asset>
                  <permission>1</permission>
                  <granted>1</granted>
                  <userid>[[system://public_user]]</userid>
              </action>
              
              <action>
                  <action_id>create_metadata_field_select_1851194910</action_id>
                  <action_type>create_asset</action_type>
                  <type_code>metadata_field_select</type_code>
                  <link_type>2</link_type>
                  <parentid>[[output://create_Metadata_Section_8864946993.assetid]]</parentid>
                  <value></value>
                  <is_dependant>1</is_dependant>
                  <is_exclusive>0</is_exclusive>
              </action> 
              <action>
                  <action_id>set_metadata_field_select_1851194910_name</action_id>
                  <action_type>set_attribute_value</action_type>
                  <asset>[[output://create_metadata_field_select_1851194910.assetid]]</asset>
                  <attribute>name</attribute>
                  <value><![CDATA[hero_image_responsive_treatment]]></value>
              </action>
              <action>
                  <action_id>set_metadata_field_select_1851194910_friendly_name</action_id>
                  <action_type>set_attribute_value</action_type>
                  <asset>[[output://create_metadata_field_select_1851194910.assetid]]</asset>
                  <attribute>friendly_name</attribute>
                  <value><![CDATA[Responsive treatment]]></value>
              </action>
              <action>
                  <action_id>set_metadata_field_select_1851194910_default</action_id>
                  <action_type>set_attribute_value</action_type>
                  <asset>[[output://create_metadata_field_select_1851194910.assetid]]</asset>
                  <attribute>default</attribute>
                  <value><![CDATA[crop]]></value>
              </action>
              <action>
                  <action_id>set_metadata_field_select_1851194910_description</action_id>
                  <action_type>set_attribute_value</action_type>
                  <asset>[[output://create_metadata_field_select_1851194910.assetid]]</asset>
                  <attribute>description</attribute>
                  <value><![CDATA[]]></value>
              </action>
              <action>
                  <action_id>set_metadata_field_select_1851194910_editable</action_id>
                  <action_type>set_attribute_value</action_type>
                  <asset>[[output://create_metadata_field_select_1851194910.assetid]]</asset>
                  <attribute>editable</attribute>
                  <value><![CDATA[1]]></value>
              </action>
              <action>
                  <action_id>set_metadata_field_select_1851194910_editable</action_id>
                  <action_type>set_attribute_value</action_type>
                  <asset>[[output://create_metadata_field_select_1851194910.assetid]]</asset>
                  <attribute>editable</attribute>
                  <value><![CDATA[1]]></value>
              </action>
              <action>
                  <action_id>set_metadata_field_select_1851194910_required</action_id>
                  <action_type>set_attribute_value</action_type>
                  <asset>[[output://create_metadata_field_select_1851194910.assetid]]</asset>
                  <attribute>required</attribute>
                  <value><![CDATA[0]]></value>
              </action>
              <action>
                  <action_id>set_permission_1851194910_read_5</action_id>
                  <action_type>set_permission</action_type>
                  <asset>[[output://create_metadata_field_select_1851194910.assetid]]</asset>
                  <permission>1</permission>
                  <granted>1</granted>
                  <userid>[[system://public_user]]</userid>
              </action>
              
                  <action>
                      <action_id>set_metadata_field_select_1851194910_select_options</action_id>
                      <action_type>set_attribute_value</action_type>
                      <asset>[[output://create_metadata_field_select_1851194910.assetid]]</asset>
                      <attribute>select_options</attribute>
                      <value><![CDATA[array ('crop' => 'Crop','scale' => 'Scale',);]]></value>
                  </action>
                  <action>
                      <action_id>set_{f.type}_1851194910_edit_params</action_id>
                      <action_type>set_attribute_value</action_type>
                      <asset>[[output://create_metadata_field_select_1851194910.assetid]]</asset>
                      <attribute>edit_params</attribute>
                      <value><![CDATA[array (
                      'style' => 'list',
                      'type' => 'table',
                      'height' => '',
                      'columns' => '1',
                      'empty_text' => '',
                      'extras' => '',
                      );]]></value>
                  </action>  
                  
              <action>
                  <action_id>create_metadata_field_select_7208496463</action_id>
                  <action_type>create_asset</action_type>
                  <type_code>metadata_field_select</type_code>
                  <link_type>2</link_type>
                  <parentid>[[output://create_Metadata_Section_8864946993.assetid]]</parentid>
                  <value></value>
                  <is_dependant>1</is_dependant>
                  <is_exclusive>0</is_exclusive>
              </action> 
              <action>
                  <action_id>set_metadata_field_select_7208496463_name</action_id>
                  <action_type>set_attribute_value</action_type>
                  <asset>[[output://create_metadata_field_select_7208496463.assetid]]</asset>
                  <attribute>name</attribute>
                  <value><![CDATA[hero_image_padding]]></value>
              </action>
              <action>
                  <action_id>set_metadata_field_select_7208496463_friendly_name</action_id>
                  <action_type>set_attribute_value</action_type>
                  <asset>[[output://create_metadata_field_select_7208496463.assetid]]</asset>
                  <attribute>friendly_name</attribute>
                  <value><![CDATA[Display Padding?]]></value>
              </action>
              <action>
                  <action_id>set_metadata_field_select_7208496463_default</action_id>
                  <action_type>set_attribute_value</action_type>
                  <asset>[[output://create_metadata_field_select_7208496463.assetid]]</asset>
                  <attribute>default</attribute>
                  <value><![CDATA[no]]></value>
              </action>
              <action>
                  <action_id>set_metadata_field_select_7208496463_description</action_id>
                  <action_type>set_attribute_value</action_type>
                  <asset>[[output://create_metadata_field_select_7208496463.assetid]]</asset>
                  <attribute>description</attribute>
                  <value><![CDATA[]]></value>
              </action>
              <action>
                  <action_id>set_metadata_field_select_7208496463_editable</action_id>
                  <action_type>set_attribute_value</action_type>
                  <asset>[[output://create_metadata_field_select_7208496463.assetid]]</asset>
                  <attribute>editable</attribute>
                  <value><![CDATA[1]]></value>
              </action>
              <action>
                  <action_id>set_metadata_field_select_7208496463_editable</action_id>
                  <action_type>set_attribute_value</action_type>
                  <asset>[[output://create_metadata_field_select_7208496463.assetid]]</asset>
                  <attribute>editable</attribute>
                  <value><![CDATA[1]]></value>
              </action>
              <action>
                  <action_id>set_metadata_field_select_7208496463_required</action_id>
                  <action_type>set_attribute_value</action_type>
                  <asset>[[output://create_metadata_field_select_7208496463.assetid]]</asset>
                  <attribute>required</attribute>
                  <value><![CDATA[0]]></value>
              </action>
              <action>
                  <action_id>set_permission_7208496463_read_5</action_id>
                  <action_type>set_permission</action_type>
                  <asset>[[output://create_metadata_field_select_7208496463.assetid]]</asset>
                  <permission>1</permission>
                  <granted>1</granted>
                  <userid>[[system://public_user]]</userid>
              </action>
              
                  <action>
                      <action_id>set_metadata_field_select_7208496463_select_options</action_id>
                      <action_type>set_attribute_value</action_type>
                      <asset>[[output://create_metadata_field_select_7208496463.assetid]]</asset>
                      <attribute>select_options</attribute>
                      <value><![CDATA[array ('no' => 'No','yes' => 'Yes',);]]></value>
                  </action>
                  <action>
                      <action_id>set_{f.type}_7208496463_edit_params</action_id>
                      <action_type>set_attribute_value</action_type>
                      <asset>[[output://create_metadata_field_select_7208496463.assetid]]</asset>
                      <attribute>edit_params</attribute>
                      <value><![CDATA[array (
                      'style' => 'list',
                      'type' => 'table',
                      'height' => '',
                      'columns' => '1',
                      'empty_text' => '',
                      'extras' => '',
                      );]]></value>
                  </action>  
                  
              <action>
                  <action_id>create_metadata_field_select_8915825429</action_id>
                  <action_type>create_asset</action_type>
                  <type_code>metadata_field_select</type_code>
                  <link_type>2</link_type>
                  <parentid>[[output://create_Metadata_Section_8864946993.assetid]]</parentid>
                  <value></value>
                  <is_dependant>1</is_dependant>
                  <is_exclusive>0</is_exclusive>
              </action> 
              <action>
                  <action_id>set_metadata_field_select_8915825429_name</action_id>
                  <action_type>set_attribute_value</action_type>
                  <asset>[[output://create_metadata_field_select_8915825429.assetid]]</asset>
                  <attribute>name</attribute>
                  <value><![CDATA[background_type]]></value>
              </action>
              <action>
                  <action_id>set_metadata_field_select_8915825429_friendly_name</action_id>
                  <action_type>set_attribute_value</action_type>
                  <asset>[[output://create_metadata_field_select_8915825429.assetid]]</asset>
                  <attribute>friendly_name</attribute>
                  <value><![CDATA[Background type]]></value>
              </action>
              <action>
                  <action_id>set_metadata_field_select_8915825429_default</action_id>
                  <action_type>set_attribute_value</action_type>
                  <asset>[[output://create_metadata_field_select_8915825429.assetid]]</asset>
                  <attribute>default</attribute>
                  <value><![CDATA[image]]></value>
              </action>
              <action>
                  <action_id>set_metadata_field_select_8915825429_description</action_id>
                  <action_type>set_attribute_value</action_type>
                  <asset>[[output://create_metadata_field_select_8915825429.assetid]]</asset>
                  <attribute>description</attribute>
                  <value><![CDATA[]]></value>
              </action>
              <action>
                  <action_id>set_metadata_field_select_8915825429_editable</action_id>
                  <action_type>set_attribute_value</action_type>
                  <asset>[[output://create_metadata_field_select_8915825429.assetid]]</asset>
                  <attribute>editable</attribute>
                  <value><![CDATA[1]]></value>
              </action>
              <action>
                  <action_id>set_metadata_field_select_8915825429_editable</action_id>
                  <action_type>set_attribute_value</action_type>
                  <asset>[[output://create_metadata_field_select_8915825429.assetid]]</asset>
                  <attribute>editable</attribute>
                  <value><![CDATA[1]]></value>
              </action>
              <action>
                  <action_id>set_metadata_field_select_8915825429_required</action_id>
                  <action_type>set_attribute_value</action_type>
                  <asset>[[output://create_metadata_field_select_8915825429.assetid]]</asset>
                  <attribute>required</attribute>
                  <value><![CDATA[0]]></value>
              </action>
              <action>
                  <action_id>set_permission_8915825429_read_5</action_id>
                  <action_type>set_permission</action_type>
                  <asset>[[output://create_metadata_field_select_8915825429.assetid]]</asset>
                  <permission>1</permission>
                  <granted>1</granted>
                  <userid>[[system://public_user]]</userid>
              </action>
              
                  <action>
                      <action_id>set_metadata_field_select_8915825429_select_options</action_id>
                      <action_type>set_attribute_value</action_type>
                      <asset>[[output://create_metadata_field_select_8915825429.assetid]]</asset>
                      <attribute>select_options</attribute>
                      <value><![CDATA[array ('colour' => 'Colour','texture' => 'Texture','image' => 'Background Image',);]]></value>
                  </action>
                  <action>
                      <action_id>set_{f.type}_8915825429_edit_params</action_id>
                      <action_type>set_attribute_value</action_type>
                      <asset>[[output://create_metadata_field_select_8915825429.assetid]]</asset>
                      <attribute>edit_params</attribute>
                      <value><![CDATA[array (
                      'style' => 'list',
                      'type' => 'table',
                      'height' => '',
                      'columns' => '1',
                      'empty_text' => '',
                      'extras' => '',
                      );]]></value>
                  </action>  
                  
              <action>
                  <action_id>create_metadata_field_select_6251310094</action_id>
                  <action_type>create_asset</action_type>
                  <type_code>metadata_field_select</type_code>
                  <link_type>2</link_type>
                  <parentid>[[output://create_Metadata_Section_8864946993.assetid]]</parentid>
                  <value></value>
                  <is_dependant>1</is_dependant>
                  <is_exclusive>0</is_exclusive>
              </action> 
              <action>
                  <action_id>set_metadata_field_select_6251310094_name</action_id>
                  <action_type>set_attribute_value</action_type>
                  <asset>[[output://create_metadata_field_select_6251310094.assetid]]</asset>
                  <attribute>name</attribute>
                  <value><![CDATA[background_colour]]></value>
              </action>
              <action>
                  <action_id>set_metadata_field_select_6251310094_friendly_name</action_id>
                  <action_type>set_attribute_value</action_type>
                  <asset>[[output://create_metadata_field_select_6251310094.assetid]]</asset>
                  <attribute>friendly_name</attribute>
                  <value><![CDATA[Background Colour]]></value>
              </action>
              <action>
                  <action_id>set_metadata_field_select_6251310094_default</action_id>
                  <action_type>set_attribute_value</action_type>
                  <asset>[[output://create_metadata_field_select_6251310094.assetid]]</asset>
                  <attribute>default</attribute>
                  <value><![CDATA[dark]]></value>
              </action>
              <action>
                  <action_id>set_metadata_field_select_6251310094_description</action_id>
                  <action_type>set_attribute_value</action_type>
                  <asset>[[output://create_metadata_field_select_6251310094.assetid]]</asset>
                  <attribute>description</attribute>
                  <value><![CDATA[]]></value>
              </action>
              <action>
                  <action_id>set_metadata_field_select_6251310094_editable</action_id>
                  <action_type>set_attribute_value</action_type>
                  <asset>[[output://create_metadata_field_select_6251310094.assetid]]</asset>
                  <attribute>editable</attribute>
                  <value><![CDATA[1]]></value>
              </action>
              <action>
                  <action_id>set_metadata_field_select_6251310094_editable</action_id>
                  <action_type>set_attribute_value</action_type>
                  <asset>[[output://create_metadata_field_select_6251310094.assetid]]</asset>
                  <attribute>editable</attribute>
                  <value><![CDATA[1]]></value>
              </action>
              <action>
                  <action_id>set_metadata_field_select_6251310094_required</action_id>
                  <action_type>set_attribute_value</action_type>
                  <asset>[[output://create_metadata_field_select_6251310094.assetid]]</asset>
                  <attribute>required</attribute>
                  <value><![CDATA[0]]></value>
              </action>
              <action>
                  <action_id>set_permission_6251310094_read_5</action_id>
                  <action_type>set_permission</action_type>
                  <asset>[[output://create_metadata_field_select_6251310094.assetid]]</asset>
                  <permission>1</permission>
                  <granted>1</granted>
                  <userid>[[system://public_user]]</userid>
              </action>
              
                  <action>
                      <action_id>set_metadata_field_select_6251310094_select_options</action_id>
                      <action_type>set_attribute_value</action_type>
                      <asset>[[output://create_metadata_field_select_6251310094.assetid]]</asset>
                      <attribute>select_options</attribute>
                      <value><![CDATA[array ('' => 'White','light' => 'Light','alternate' => 'Alternate','dark' => 'Dark','dark-alternate' => 'Dark Alternate',);]]></value>
                  </action>
                  <action>
                      <action_id>set_{f.type}_6251310094_edit_params</action_id>
                      <action_type>set_attribute_value</action_type>
                      <asset>[[output://create_metadata_field_select_6251310094.assetid]]</asset>
                      <attribute>edit_params</attribute>
                      <value><![CDATA[array (
                      'style' => 'list',
                      'type' => 'table',
                      'height' => '',
                      'columns' => '1',
                      'empty_text' => '',
                      'extras' => '',
                      );]]></value>
                  </action>  
                  
              <action>
                  <action_id>create_metadata_field_related_asset_7844945848</action_id>
                  <action_type>create_asset</action_type>
                  <type_code>metadata_field_related_asset</type_code>
                  <link_type>2</link_type>
                  <parentid>[[output://create_Metadata_Section_8864946993.assetid]]</parentid>
                  <value></value>
                  <is_dependant>1</is_dependant>
                  <is_exclusive>0</is_exclusive>
              </action> 
              <action>
                  <action_id>set_metadata_field_related_asset_7844945848_name</action_id>
                  <action_type>set_attribute_value</action_type>
                  <asset>[[output://create_metadata_field_related_asset_7844945848.assetid]]</asset>
                  <attribute>name</attribute>
                  <value><![CDATA[background_image_sm]]></value>
              </action>
              <action>
                  <action_id>set_metadata_field_related_asset_7844945848_friendly_name</action_id>
                  <action_type>set_attribute_value</action_type>
                  <asset>[[output://create_metadata_field_related_asset_7844945848.assetid]]</asset>
                  <attribute>friendly_name</attribute>
                  <value><![CDATA[Background Image - Mobile]]></value>
              </action>
              <action>
                  <action_id>set_metadata_field_related_asset_7844945848_default</action_id>
                  <action_type>set_attribute_value</action_type>
                  <asset>[[output://create_metadata_field_related_asset_7844945848.assetid]]</asset>
                  <attribute>default</attribute>
                  <value><![CDATA[/mysource_files/banner-bg.png]]></value>
              </action>
              <action>
                  <action_id>set_metadata_field_related_asset_7844945848_description</action_id>
                  <action_type>set_attribute_value</action_type>
                  <asset>[[output://create_metadata_field_related_asset_7844945848.assetid]]</asset>
                  <attribute>description</attribute>
                  <value><![CDATA[]]></value>
              </action>
              <action>
                  <action_id>set_metadata_field_related_asset_7844945848_editable</action_id>
                  <action_type>set_attribute_value</action_type>
                  <asset>[[output://create_metadata_field_related_asset_7844945848.assetid]]</asset>
                  <attribute>editable</attribute>
                  <value><![CDATA[1]]></value>
              </action>
              <action>
                  <action_id>set_metadata_field_related_asset_7844945848_editable</action_id>
                  <action_type>set_attribute_value</action_type>
                  <asset>[[output://create_metadata_field_related_asset_7844945848.assetid]]</asset>
                  <attribute>editable</attribute>
                  <value><![CDATA[1]]></value>
              </action>
              <action>
                  <action_id>set_metadata_field_related_asset_7844945848_required</action_id>
                  <action_type>set_attribute_value</action_type>
                  <asset>[[output://create_metadata_field_related_asset_7844945848.assetid]]</asset>
                  <attribute>required</attribute>
                  <value><![CDATA[0]]></value>
              </action>
              <action>
                  <action_id>set_permission_7844945848_read_5</action_id>
                  <action_type>set_permission</action_type>
                  <asset>[[output://create_metadata_field_related_asset_7844945848.assetid]]</asset>
                  <permission>1</permission>
                  <granted>1</granted>
                  <userid>[[system://public_user]]</userid>
              </action>
              
              <action>
                  <action_id>create_metadata_field_related_asset_1827171175</action_id>
                  <action_type>create_asset</action_type>
                  <type_code>metadata_field_related_asset</type_code>
                  <link_type>2</link_type>
                  <parentid>[[output://create_Metadata_Section_8864946993.assetid]]</parentid>
                  <value></value>
                  <is_dependant>1</is_dependant>
                  <is_exclusive>0</is_exclusive>
              </action> 
              <action>
                  <action_id>set_metadata_field_related_asset_1827171175_name</action_id>
                  <action_type>set_attribute_value</action_type>
                  <asset>[[output://create_metadata_field_related_asset_1827171175.assetid]]</asset>
                  <attribute>name</attribute>
                  <value><![CDATA[background_image_lg]]></value>
              </action>
              <action>
                  <action_id>set_metadata_field_related_asset_1827171175_friendly_name</action_id>
                  <action_type>set_attribute_value</action_type>
                  <asset>[[output://create_metadata_field_related_asset_1827171175.assetid]]</asset>
                  <attribute>friendly_name</attribute>
                  <value><![CDATA[Background Image - Desktop and Tablet]]></value>
              </action>
              <action>
                  <action_id>set_metadata_field_related_asset_1827171175_default</action_id>
                  <action_type>set_attribute_value</action_type>
                  <asset>[[output://create_metadata_field_related_asset_1827171175.assetid]]</asset>
                  <attribute>default</attribute>
                  <value><![CDATA[/mysource_files/banner-bg.png]]></value>
              </action>
              <action>
                  <action_id>set_metadata_field_related_asset_1827171175_description</action_id>
                  <action_type>set_attribute_value</action_type>
                  <asset>[[output://create_metadata_field_related_asset_1827171175.assetid]]</asset>
                  <attribute>description</attribute>
                  <value><![CDATA[]]></value>
              </action>
              <action>
                  <action_id>set_metadata_field_related_asset_1827171175_editable</action_id>
                  <action_type>set_attribute_value</action_type>
                  <asset>[[output://create_metadata_field_related_asset_1827171175.assetid]]</asset>
                  <attribute>editable</attribute>
                  <value><![CDATA[1]]></value>
              </action>
              <action>
                  <action_id>set_metadata_field_related_asset_1827171175_editable</action_id>
                  <action_type>set_attribute_value</action_type>
                  <asset>[[output://create_metadata_field_related_asset_1827171175.assetid]]</asset>
                  <attribute>editable</attribute>
                  <value><![CDATA[1]]></value>
              </action>
              <action>
                  <action_id>set_metadata_field_related_asset_1827171175_required</action_id>
                  <action_type>set_attribute_value</action_type>
                  <asset>[[output://create_metadata_field_related_asset_1827171175.assetid]]</asset>
                  <attribute>required</attribute>
                  <value><![CDATA[0]]></value>
              </action>
              <action>
                  <action_id>set_permission_1827171175_read_5</action_id>
                  <action_type>set_permission</action_type>
                  <asset>[[output://create_metadata_field_related_asset_1827171175.assetid]]</asset>
                  <permission>1</permission>
                  <granted>1</granted>
                  <userid>[[system://public_user]]</userid>
              </action>
              
              <action>
                  <action_id>create_metadata_field_select_5420791417</action_id>
                  <action_type>create_asset</action_type>
                  <type_code>metadata_field_select</type_code>
                  <link_type>2</link_type>
                  <parentid>[[output://create_Metadata_Section_8864946993.assetid]]</parentid>
                  <value></value>
                  <is_dependant>1</is_dependant>
                  <is_exclusive>0</is_exclusive>
              </action> 
              <action>
                  <action_id>set_metadata_field_select_5420791417_name</action_id>
                  <action_type>set_attribute_value</action_type>
                  <asset>[[output://create_metadata_field_select_5420791417.assetid]]</asset>
                  <attribute>name</attribute>
                  <value><![CDATA[background_image_alignment]]></value>
              </action>
              <action>
                  <action_id>set_metadata_field_select_5420791417_friendly_name</action_id>
                  <action_type>set_attribute_value</action_type>
                  <asset>[[output://create_metadata_field_select_5420791417.assetid]]</asset>
                  <attribute>friendly_name</attribute>
                  <value><![CDATA[Background alignment]]></value>
              </action>
              <action>
                  <action_id>set_metadata_field_select_5420791417_default</action_id>
                  <action_type>set_attribute_value</action_type>
                  <asset>[[output://create_metadata_field_select_5420791417.assetid]]</asset>
                  <attribute>default</attribute>
                  <value><![CDATA[center]]></value>
              </action>
              <action>
                  <action_id>set_metadata_field_select_5420791417_description</action_id>
                  <action_type>set_attribute_value</action_type>
                  <asset>[[output://create_metadata_field_select_5420791417.assetid]]</asset>
                  <attribute>description</attribute>
                  <value><![CDATA[]]></value>
              </action>
              <action>
                  <action_id>set_metadata_field_select_5420791417_editable</action_id>
                  <action_type>set_attribute_value</action_type>
                  <asset>[[output://create_metadata_field_select_5420791417.assetid]]</asset>
                  <attribute>editable</attribute>
                  <value><![CDATA[1]]></value>
              </action>
              <action>
                  <action_id>set_metadata_field_select_5420791417_editable</action_id>
                  <action_type>set_attribute_value</action_type>
                  <asset>[[output://create_metadata_field_select_5420791417.assetid]]</asset>
                  <attribute>editable</attribute>
                  <value><![CDATA[1]]></value>
              </action>
              <action>
                  <action_id>set_metadata_field_select_5420791417_required</action_id>
                  <action_type>set_attribute_value</action_type>
                  <asset>[[output://create_metadata_field_select_5420791417.assetid]]</asset>
                  <attribute>required</attribute>
                  <value><![CDATA[0]]></value>
              </action>
              <action>
                  <action_id>set_permission_5420791417_read_5</action_id>
                  <action_type>set_permission</action_type>
                  <asset>[[output://create_metadata_field_select_5420791417.assetid]]</asset>
                  <permission>1</permission>
                  <granted>1</granted>
                  <userid>[[system://public_user]]</userid>
              </action>
              
                  <action>
                      <action_id>set_metadata_field_select_5420791417_select_options</action_id>
                      <action_type>set_attribute_value</action_type>
                      <asset>[[output://create_metadata_field_select_5420791417.assetid]]</asset>
                      <attribute>select_options</attribute>
                      <value><![CDATA[array ('left' => 'Left','right' => 'Right','center' => 'Center',);]]></value>
                  </action>
                  <action>
                      <action_id>set_{f.type}_5420791417_edit_params</action_id>
                      <action_type>set_attribute_value</action_type>
                      <asset>[[output://create_metadata_field_select_5420791417.assetid]]</asset>
                      <attribute>edit_params</attribute>
                      <value><![CDATA[array (
                      'style' => 'list',
                      'type' => 'table',
                      'height' => '',
                      'columns' => '1',
                      'empty_text' => '',
                      'extras' => '',
                      );]]></value>
                  </action>  
                  
              <action>
                  <action_id>create_metadata_field_text_3685364696</action_id>
                  <action_type>create_asset</action_type>
                  <type_code>metadata_field_text</type_code>
                  <link_type>2</link_type>
                  <parentid>[[output://create_Metadata_Section_8864946993.assetid]]</parentid>
                  <value></value>
                  <is_dependant>1</is_dependant>
                  <is_exclusive>0</is_exclusive>
              </action> 
              <action>
                  <action_id>set_metadata_field_text_3685364696_name</action_id>
                  <action_type>set_attribute_value</action_type>
                  <asset>[[output://create_metadata_field_text_3685364696.assetid]]</asset>
                  <attribute>name</attribute>
                  <value><![CDATA[cta_button_primary_text]]></value>
              </action>
              <action>
                  <action_id>set_metadata_field_text_3685364696_friendly_name</action_id>
                  <action_type>set_attribute_value</action_type>
                  <asset>[[output://create_metadata_field_text_3685364696.assetid]]</asset>
                  <attribute>friendly_name</attribute>
                  <value><![CDATA[Primary Button Text]]></value>
              </action>
              <action>
                  <action_id>set_metadata_field_text_3685364696_default</action_id>
                  <action_type>set_attribute_value</action_type>
                  <asset>[[output://create_metadata_field_text_3685364696.assetid]]</asset>
                  <attribute>default</attribute>
                  <value><![CDATA[Primary Button]]></value>
              </action>
              <action>
                  <action_id>set_metadata_field_text_3685364696_description</action_id>
                  <action_type>set_attribute_value</action_type>
                  <asset>[[output://create_metadata_field_text_3685364696.assetid]]</asset>
                  <attribute>description</attribute>
                  <value><![CDATA[]]></value>
              </action>
              <action>
                  <action_id>set_metadata_field_text_3685364696_editable</action_id>
                  <action_type>set_attribute_value</action_type>
                  <asset>[[output://create_metadata_field_text_3685364696.assetid]]</asset>
                  <attribute>editable</attribute>
                  <value><![CDATA[1]]></value>
              </action>
              <action>
                  <action_id>set_metadata_field_text_3685364696_editable</action_id>
                  <action_type>set_attribute_value</action_type>
                  <asset>[[output://create_metadata_field_text_3685364696.assetid]]</asset>
                  <attribute>editable</attribute>
                  <value><![CDATA[1]]></value>
              </action>
              <action>
                  <action_id>set_metadata_field_text_3685364696_required</action_id>
                  <action_type>set_attribute_value</action_type>
                  <asset>[[output://create_metadata_field_text_3685364696.assetid]]</asset>
                  <attribute>required</attribute>
                  <value><![CDATA[0]]></value>
              </action>
              <action>
                  <action_id>set_permission_3685364696_read_5</action_id>
                  <action_type>set_permission</action_type>
                  <asset>[[output://create_metadata_field_text_3685364696.assetid]]</asset>
                  <permission>1</permission>
                  <granted>1</granted>
                  <userid>[[system://public_user]]</userid>
              </action>
              
              <action>
                  <action_id>create_metadata_field_related_asset_4903304172</action_id>
                  <action_type>create_asset</action_type>
                  <type_code>metadata_field_related_asset</type_code>
                  <link_type>2</link_type>
                  <parentid>[[output://create_Metadata_Section_8864946993.assetid]]</parentid>
                  <value></value>
                  <is_dependant>1</is_dependant>
                  <is_exclusive>0</is_exclusive>
              </action> 
              <action>
                  <action_id>set_metadata_field_related_asset_4903304172_name</action_id>
                  <action_type>set_attribute_value</action_type>
                  <asset>[[output://create_metadata_field_related_asset_4903304172.assetid]]</asset>
                  <attribute>name</attribute>
                  <value><![CDATA[cta_button_primary_link]]></value>
              </action>
              <action>
                  <action_id>set_metadata_field_related_asset_4903304172_friendly_name</action_id>
                  <action_type>set_attribute_value</action_type>
                  <asset>[[output://create_metadata_field_related_asset_4903304172.assetid]]</asset>
                  <attribute>friendly_name</attribute>
                  <value><![CDATA[Primary Button Link]]></value>
              </action>
              <action>
                  <action_id>set_metadata_field_related_asset_4903304172_default</action_id>
                  <action_type>set_attribute_value</action_type>
                  <asset>[[output://create_metadata_field_related_asset_4903304172.assetid]]</asset>
                  <attribute>default</attribute>
                  <value><![CDATA[#]]></value>
              </action>
              <action>
                  <action_id>set_metadata_field_related_asset_4903304172_description</action_id>
                  <action_type>set_attribute_value</action_type>
                  <asset>[[output://create_metadata_field_related_asset_4903304172.assetid]]</asset>
                  <attribute>description</attribute>
                  <value><![CDATA[]]></value>
              </action>
              <action>
                  <action_id>set_metadata_field_related_asset_4903304172_editable</action_id>
                  <action_type>set_attribute_value</action_type>
                  <asset>[[output://create_metadata_field_related_asset_4903304172.assetid]]</asset>
                  <attribute>editable</attribute>
                  <value><![CDATA[1]]></value>
              </action>
              <action>
                  <action_id>set_metadata_field_related_asset_4903304172_editable</action_id>
                  <action_type>set_attribute_value</action_type>
                  <asset>[[output://create_metadata_field_related_asset_4903304172.assetid]]</asset>
                  <attribute>editable</attribute>
                  <value><![CDATA[1]]></value>
              </action>
              <action>
                  <action_id>set_metadata_field_related_asset_4903304172_required</action_id>
                  <action_type>set_attribute_value</action_type>
                  <asset>[[output://create_metadata_field_related_asset_4903304172.assetid]]</asset>
                  <attribute>required</attribute>
                  <value><![CDATA[0]]></value>
              </action>
              <action>
                  <action_id>set_permission_4903304172_read_5</action_id>
                  <action_type>set_permission</action_type>
                  <asset>[[output://create_metadata_field_related_asset_4903304172.assetid]]</asset>
                  <permission>1</permission>
                  <granted>1</granted>
                  <userid>[[system://public_user]]</userid>
              </action>
              
              <action>
                  <action_id>create_metadata_field_text_1894053312</action_id>
                  <action_type>create_asset</action_type>
                  <type_code>metadata_field_text</type_code>
                  <link_type>2</link_type>
                  <parentid>[[output://create_Metadata_Section_8864946993.assetid]]</parentid>
                  <value></value>
                  <is_dependant>1</is_dependant>
                  <is_exclusive>0</is_exclusive>
              </action> 
              <action>
                  <action_id>set_metadata_field_text_1894053312_name</action_id>
                  <action_type>set_attribute_value</action_type>
                  <asset>[[output://create_metadata_field_text_1894053312.assetid]]</asset>
                  <attribute>name</attribute>
                  <value><![CDATA[cta_button_secondary_text]]></value>
              </action>
              <action>
                  <action_id>set_metadata_field_text_1894053312_friendly_name</action_id>
                  <action_type>set_attribute_value</action_type>
                  <asset>[[output://create_metadata_field_text_1894053312.assetid]]</asset>
                  <attribute>friendly_name</attribute>
                  <value><![CDATA[Secondary Button Text]]></value>
              </action>
              <action>
                  <action_id>set_metadata_field_text_1894053312_default</action_id>
                  <action_type>set_attribute_value</action_type>
                  <asset>[[output://create_metadata_field_text_1894053312.assetid]]</asset>
                  <attribute>default</attribute>
                  <value><![CDATA[Secondary Button]]></value>
              </action>
              <action>
                  <action_id>set_metadata_field_text_1894053312_description</action_id>
                  <action_type>set_attribute_value</action_type>
                  <asset>[[output://create_metadata_field_text_1894053312.assetid]]</asset>
                  <attribute>description</attribute>
                  <value><![CDATA[]]></value>
              </action>
              <action>
                  <action_id>set_metadata_field_text_1894053312_editable</action_id>
                  <action_type>set_attribute_value</action_type>
                  <asset>[[output://create_metadata_field_text_1894053312.assetid]]</asset>
                  <attribute>editable</attribute>
                  <value><![CDATA[1]]></value>
              </action>
              <action>
                  <action_id>set_metadata_field_text_1894053312_editable</action_id>
                  <action_type>set_attribute_value</action_type>
                  <asset>[[output://create_metadata_field_text_1894053312.assetid]]</asset>
                  <attribute>editable</attribute>
                  <value><![CDATA[1]]></value>
              </action>
              <action>
                  <action_id>set_metadata_field_text_1894053312_required</action_id>
                  <action_type>set_attribute_value</action_type>
                  <asset>[[output://create_metadata_field_text_1894053312.assetid]]</asset>
                  <attribute>required</attribute>
                  <value><![CDATA[0]]></value>
              </action>
              <action>
                  <action_id>set_permission_1894053312_read_5</action_id>
                  <action_type>set_permission</action_type>
                  <asset>[[output://create_metadata_field_text_1894053312.assetid]]</asset>
                  <permission>1</permission>
                  <granted>1</granted>
                  <userid>[[system://public_user]]</userid>
              </action>
              
              <action>
                  <action_id>create_metadata_field_related_asset_2534426511</action_id>
                  <action_type>create_asset</action_type>
                  <type_code>metadata_field_related_asset</type_code>
                  <link_type>2</link_type>
                  <parentid>[[output://create_Metadata_Section_8864946993.assetid]]</parentid>
                  <value></value>
                  <is_dependant>1</is_dependant>
                  <is_exclusive>0</is_exclusive>
              </action> 
              <action>
                  <action_id>set_metadata_field_related_asset_2534426511_name</action_id>
                  <action_type>set_attribute_value</action_type>
                  <asset>[[output://create_metadata_field_related_asset_2534426511.assetid]]</asset>
                  <attribute>name</attribute>
                  <value><![CDATA[cta_button_secondary_link]]></value>
              </action>
              <action>
                  <action_id>set_metadata_field_related_asset_2534426511_friendly_name</action_id>
                  <action_type>set_attribute_value</action_type>
                  <asset>[[output://create_metadata_field_related_asset_2534426511.assetid]]</asset>
                  <attribute>friendly_name</attribute>
                  <value><![CDATA[Secondary Button Link]]></value>
              </action>
              <action>
                  <action_id>set_metadata_field_related_asset_2534426511_default</action_id>
                  <action_type>set_attribute_value</action_type>
                  <asset>[[output://create_metadata_field_related_asset_2534426511.assetid]]</asset>
                  <attribute>default</attribute>
                  <value><![CDATA[#]]></value>
              </action>
              <action>
                  <action_id>set_metadata_field_related_asset_2534426511_description</action_id>
                  <action_type>set_attribute_value</action_type>
                  <asset>[[output://create_metadata_field_related_asset_2534426511.assetid]]</asset>
                  <attribute>description</attribute>
                  <value><![CDATA[]]></value>
              </action>
              <action>
                  <action_id>set_metadata_field_related_asset_2534426511_editable</action_id>
                  <action_type>set_attribute_value</action_type>
                  <asset>[[output://create_metadata_field_related_asset_2534426511.assetid]]</asset>
                  <attribute>editable</attribute>
                  <value><![CDATA[1]]></value>
              </action>
              <action>
                  <action_id>set_metadata_field_related_asset_2534426511_editable</action_id>
                  <action_type>set_attribute_value</action_type>
                  <asset>[[output://create_metadata_field_related_asset_2534426511.assetid]]</asset>
                  <attribute>editable</attribute>
                  <value><![CDATA[1]]></value>
              </action>
              <action>
                  <action_id>set_metadata_field_related_asset_2534426511_required</action_id>
                  <action_type>set_attribute_value</action_type>
                  <asset>[[output://create_metadata_field_related_asset_2534426511.assetid]]</asset>
                  <attribute>required</attribute>
                  <value><![CDATA[0]]></value>
              </action>
              <action>
                  <action_id>set_permission_2534426511_read_5</action_id>
                  <action_type>set_permission</action_type>
                  <asset>[[output://create_metadata_field_related_asset_2534426511.assetid]]</asset>
                  <permission>1</permission>
                  <granted>1</granted>
                  <userid>[[system://public_user]]</userid>
              </action>
              
              <action>
                  <action_id>create_metadata_field_text_6635798036</action_id>
                  <action_type>create_asset</action_type>
                  <type_code>metadata_field_text</type_code>
                  <link_type>2</link_type>
                  <parentid>[[output://create_Metadata_Section_8864946993.assetid]]</parentid>
                  <value></value>
                  <is_dependant>1</is_dependant>
                  <is_exclusive>0</is_exclusive>
              </action> 
              <action>
                  <action_id>set_metadata_field_text_6635798036_name</action_id>
                  <action_type>set_attribute_value</action_type>
                  <asset>[[output://create_metadata_field_text_6635798036.assetid]]</asset>
                  <attribute>name</attribute>
                  <value><![CDATA[id_field]]></value>
              </action>
              <action>
                  <action_id>set_metadata_field_text_6635798036_friendly_name</action_id>
                  <action_type>set_attribute_value</action_type>
                  <asset>[[output://create_metadata_field_text_6635798036.assetid]]</asset>
                  <attribute>friendly_name</attribute>
                  <value><![CDATA[Id field]]></value>
              </action>
              <action>
                  <action_id>set_metadata_field_text_6635798036_default</action_id>
                  <action_type>set_attribute_value</action_type>
                  <asset>[[output://create_metadata_field_text_6635798036.assetid]]</asset>
                  <attribute>default</attribute>
                  <value><![CDATA[]]></value>
              </action>
              <action>
                  <action_id>set_metadata_field_text_6635798036_description</action_id>
                  <action_type>set_attribute_value</action_type>
                  <asset>[[output://create_metadata_field_text_6635798036.assetid]]</asset>
                  <attribute>description</attribute>
                  <value><![CDATA[]]></value>
              </action>
              <action>
                  <action_id>set_metadata_field_text_6635798036_editable</action_id>
                  <action_type>set_attribute_value</action_type>
                  <asset>[[output://create_metadata_field_text_6635798036.assetid]]</asset>
                  <attribute>editable</attribute>
                  <value><![CDATA[1]]></value>
              </action>
              <action>
                  <action_id>set_metadata_field_text_6635798036_editable</action_id>
                  <action_type>set_attribute_value</action_type>
                  <asset>[[output://create_metadata_field_text_6635798036.assetid]]</asset>
                  <attribute>editable</attribute>
                  <value><![CDATA[1]]></value>
              </action>
              <action>
                  <action_id>set_metadata_field_text_6635798036_required</action_id>
                  <action_type>set_attribute_value</action_type>
                  <asset>[[output://create_metadata_field_text_6635798036.assetid]]</asset>
                  <attribute>required</attribute>
                  <value><![CDATA[0]]></value>
              </action>
              <action>
                  <action_id>set_permission_6635798036_read_5</action_id>
                  <action_type>set_permission</action_type>
                  <asset>[[output://create_metadata_field_text_6635798036.assetid]]</asset>
                  <permission>1</permission>
                  <granted>1</granted>
                  <userid>[[system://public_user]]</userid>
              </action>
              </actions>